Compiled from "TypeIO.java"
public class mindustry.io.TypeIO {
  static final mindustry.entities.units.WeaponMount[] noMounts;

  static final mindustry.entities.abilities.Ability[] noAbilities;

  public mindustry.io.TypeIO();
    Code:
       0: aload_0
       1: invokespecial #1                  // Method java/lang/Object."<init>":()V
       4: return

  public static void writeObject(arc.util.io.Writes, java.lang.Object);
    Code:
       0: aload_1
       1: ifnonnull     12
       4: aload_0
       5: iconst_0
       6: invokevirtual #7                  // Method arc/util/io/Writes.b:(I)V
       9: goto          1016
      12: aload_1
      13: instanceof    #13                 // class java/lang/Integer
      16: ifeq          40
      19: aload_1
      20: checkcast     #13                 // class java/lang/Integer
      23: astore_3
      24: aload_0
      25: iconst_1
      26: invokevirtual #7                  // Method arc/util/io/Writes.b:(I)V
      29: aload_0
      30: aload_3
      31: invokevirtual #15                 // Method java/lang/Integer.intValue:()I
      34: invokevirtual #19                 // Method arc/util/io/Writes.i:(I)V
      37: goto          1016
      40: aload_1
      41: instanceof    #22                 // class java/lang/Long
      44: ifeq          70
      47: aload_1
      48: checkcast     #22                 // class java/lang/Long
      51: astore        4
      53: aload_0
      54: iconst_2
      55: invokevirtual #7                  // Method arc/util/io/Writes.b:(I)V
      58: aload_0
      59: aload         4
      61: invokevirtual #24                 // Method java/lang/Long.longValue:()J
      64: invokevirtual #28                 // Method arc/util/io/Writes.l:(J)V
      67: goto          1016
      70: aload_1
      71: instanceof    #32                 // class java/lang/Float
      74: ifeq          100
      77: aload_1
      78: checkcast     #32                 // class java/lang/Float
      81: astore        5
      83: aload_0
      84: iconst_3
      85: invokevirtual #7                  // Method arc/util/io/Writes.b:(I)V
      88: aload_0
      89: aload         5
      91: invokevirtual #34                 // Method java/lang/Float.floatValue:()F
      94: invokevirtual #38                 // Method arc/util/io/Writes.f:(F)V
      97: goto          1016
     100: aload_1
     101: instanceof    #42                 // class java/lang/String
     104: ifeq          127
     107: aload_1
     108: checkcast     #42                 // class java/lang/String
     111: astore        6
     113: aload_0
     114: iconst_4
     115: invokevirtual #7                  // Method arc/util/io/Writes.b:(I)V
     118: aload_0
     119: aload         6
     121: invokestatic  #44                 // Method writeString:(Larc/util/io/Writes;Ljava/lang/String;)V
     124: goto          1016
     127: aload_1
     128: instanceof    #50                 // class mindustry/ctype/Content
     131: ifeq          170
     134: aload_1
     135: checkcast     #50                 // class mindustry/ctype/Content
     138: astore        7
     140: aload_0
     141: iconst_5
     142: invokevirtual #7                  // Method arc/util/io/Writes.b:(I)V
     145: aload_0
     146: aload         7
     148: invokevirtual #52                 // Method mindustry/ctype/Content.getContentType:()Lmindustry/ctype/ContentType;
     151: invokevirtual #56                 // Method mindustry/ctype/ContentType.ordinal:()I
     154: i2b
     155: invokevirtual #7                  // Method arc/util/io/Writes.b:(I)V
     158: aload_0
     159: aload         7
     161: getfield      #61                 // Field mindustry/ctype/Content.id:S
     164: invokevirtual #65                 // Method arc/util/io/Writes.s:(I)V
     167: goto          1016
     170: aload_1
     171: instanceof    #68                 // class arc/struct/IntSeq
     174: ifeq          233
     177: aload_1
     178: checkcast     #68                 // class arc/struct/IntSeq
     181: astore        8
     183: aload_0
     184: bipush        6
     186: invokevirtual #7                  // Method arc/util/io/Writes.b:(I)V
     189: aload_0
     190: aload         8
     192: getfield      #70                 // Field arc/struct/IntSeq.size:I
     195: i2s
     196: invokevirtual #65                 // Method arc/util/io/Writes.s:(I)V
     199: iconst_0
     200: istore        26
     202: iload         26
     204: aload         8
     206: getfield      #70                 // Field arc/struct/IntSeq.size:I
     209: if_icmpge     230
     212: aload_0
     213: aload         8
     215: getfield      #74                 // Field arc/struct/IntSeq.items:[I
     218: iload         26
     220: iaload
     221: invokevirtual #19                 // Method arc/util/io/Writes.i:(I)V
     224: iinc          26, 1
     227: goto          202
     230: goto          1016
     233: aload_1
     234: instanceof    #78                 // class arc/math/geom/Point2
     237: ifeq          273
     240: aload_1
     241: checkcast     #78                 // class arc/math/geom/Point2
     244: astore        9
     246: aload_0
     247: bipush        7
     249: invokevirtual #7                  // Method arc/util/io/Writes.b:(I)V
     252: aload_0
     253: aload         9
     255: getfield      #80                 // Field arc/math/geom/Point2.x:I
     258: invokevirtual #19                 // Method arc/util/io/Writes.i:(I)V
     261: aload_0
     262: aload         9
     264: getfield      #83                 // Field arc/math/geom/Point2.y:I
     267: invokevirtual #19                 // Method arc/util/io/Writes.i:(I)V
     270: goto          1016
     273: aload_1
     274: instanceof    #86                 // class "[Larc/math/geom/Point2;"
     277: ifeq          343
     280: aload_1
     281: checkcast     #86                 // class "[Larc/math/geom/Point2;"
     284: astore        10
     286: aload_0
     287: bipush        8
     289: invokevirtual #7                  // Method arc/util/io/Writes.b:(I)V
     292: aload_0
     293: aload         10
     295: arraylength
     296: invokevirtual #7                  // Method arc/util/io/Writes.b:(I)V
     299: aload         10
     301: astore        26
     303: aload         26
     305: arraylength
     306: istore        27
     308: iconst_0
     309: istore        28
     311: iload         28
     313: iload         27
     315: if_icmpge     340
     318: aload         26
     320: iload         28
     322: aaload
     323: astore        29
     325: aload_0
     326: aload         29
     328: invokevirtual #88                 // Method arc/math/geom/Point2.pack:()I
     331: invokevirtual #19                 // Method arc/util/io/Writes.i:(I)V
     334: iinc          28, 1
     337: goto          311
     340: goto          1016
     343: aload_1
     344: instanceof    #91                 // class mindustry/content/TechTree$TechNode
     347: ifeq          393
     350: aload_1
     351: checkcast     #91                 // class mindustry/content/TechTree$TechNode
     354: astore        11
     356: aload_0
     357: bipush        9
     359: invokevirtual #7                  // Method arc/util/io/Writes.b:(I)V
     362: aload_0
     363: aload         11
     365: getfield      #93                 // Field mindustry/content/TechTree$TechNode.content:Lmindustry/ctype/UnlockableContent;
     368: invokevirtual #97                 // Method mindustry/ctype/UnlockableContent.getContentType:()Lmindustry/ctype/ContentType;
     371: invokevirtual #56                 // Method mindustry/ctype/ContentType.ordinal:()I
     374: i2b
     375: invokevirtual #7                  // Method arc/util/io/Writes.b:(I)V
     378: aload_0
     379: aload         11
     381: getfield      #93                 // Field mindustry/content/TechTree$TechNode.content:Lmindustry/ctype/UnlockableContent;
     384: getfield      #100                // Field mindustry/ctype/UnlockableContent.id:S
     387: invokevirtual #65                 // Method arc/util/io/Writes.s:(I)V
     390: goto          1016
     393: aload_1
     394: instanceof    #101                // class java/lang/Boolean
     397: ifeq          424
     400: aload_1
     401: checkcast     #101                // class java/lang/Boolean
     404: astore        12
     406: aload_0
     407: bipush        10
     409: invokevirtual #7                  // Method arc/util/io/Writes.b:(I)V
     412: aload_0
     413: aload         12
     415: invokevirtual #103                // Method java/lang/Boolean.booleanValue:()Z
     418: invokevirtual #107                // Method arc/util/io/Writes.bool:(Z)V
     421: goto          1016
     424: aload_1
     425: instanceof    #111                // class java/lang/Double
     428: ifeq          455
     431: aload_1
     432: checkcast     #111                // class java/lang/Double
     435: astore        13
     437: aload_0
     438: bipush        11
     440: invokevirtual #7                  // Method arc/util/io/Writes.b:(I)V
     443: aload_0
     444: aload         13
     446: invokevirtual #113                // Method java/lang/Double.doubleValue:()D
     449: invokevirtual #117                // Method arc/util/io/Writes.d:(D)V
     452: goto          1016
     455: aload_1
     456: instanceof    #121                // class mindustry/gen/Building
     459: ifeq          486
     462: aload_1
     463: checkcast     #121                // class mindustry/gen/Building
     466: astore        14
     468: aload_0
     469: bipush        12
     471: invokevirtual #7                  // Method arc/util/io/Writes.b:(I)V
     474: aload_0
     475: aload         14
     477: invokevirtual #123                // Method mindustry/gen/Building.pos:()I
     480: invokevirtual #19                 // Method arc/util/io/Writes.i:(I)V
     483: goto          1016
     486: aload_1
     487: instanceof    #126                // class mindustry/io/TypeIO$BuildingBox
     490: ifeq          517
     493: aload_1
     494: checkcast     #126                // class mindustry/io/TypeIO$BuildingBox
     497: astore        15
     499: aload_0
     500: bipush        12
     502: invokevirtual #7                  // Method arc/util/io/Writes.b:(I)V
     505: aload_0
     506: aload         15
     508: getfield      #128                // Field mindustry/io/TypeIO$BuildingBox.pos:I
     511: invokevirtual #19                 // Method arc/util/io/Writes.i:(I)V
     514: goto          1016
     517: aload_1
     518: instanceof    #130                // class mindustry/logic/LAccess
     521: ifeq          548
     524: aload_1
     525: checkcast     #130                // class mindustry/logic/LAccess
     528: astore        16
     530: aload_0
     531: bipush        13
     533: invokevirtual #7                  // Method arc/util/io/Writes.b:(I)V
     536: aload_0
     537: aload         16
     539: invokevirtual #132                // Method mindustry/logic/LAccess.ordinal:()I
     542: invokevirtual #65                 // Method arc/util/io/Writes.s:(I)V
     545: goto          1016
     548: aload_1
     549: instanceof    #133                // class "[B"
     552: ifeq          583
     555: aload_1
     556: checkcast     #133                // class "[B"
     559: astore        17
     561: aload_0
     562: bipush        14
     564: invokevirtual #7                  // Method arc/util/io/Writes.b:(I)V
     567: aload_0
     568: aload         17
     570: arraylength
     571: invokevirtual #19                 // Method arc/util/io/Writes.i:(I)V
     574: aload_0
     575: aload         17
     577: invokevirtual #135                // Method arc/util/io/Writes.b:([B)V
     580: goto          1016
     583: aload_1
     584: instanceof    #138                // class "[Z"
     587: ifeq          650
     590: aload_1
     591: checkcast     #138                // class "[Z"
     594: astore        18
     596: aload_0
     597: bipush        16
     599: invokevirtual #7                  // Method arc/util/io/Writes.b:(I)V
     602: aload_0
     603: aload         18
     605: arraylength
     606: invokevirtual #19                 // Method arc/util/io/Writes.i:(I)V
     609: aload         18
     611: astore        26
     613: aload         26
     615: arraylength
     616: istore        27
     618: iconst_0
     619: istore        28
     621: iload         28
     623: iload         27
     625: if_icmpge     647
     628: aload         26
     630: iload         28
     632: baload
     633: istore        29
     635: aload_0
     636: iload         29
     638: invokevirtual #107                // Method arc/util/io/Writes.bool:(Z)V
     641: iinc          28, 1
     644: goto          621
     647: goto          1016
     650: aload_1
     651: instanceof    #140                // class mindustry/gen/Unit
     654: ifeq          681
     657: aload_1
     658: checkcast     #140                // class mindustry/gen/Unit
     661: astore        19
     663: aload_0
     664: bipush        17
     666: invokevirtual #7                  // Method arc/util/io/Writes.b:(I)V
     669: aload_0
     670: aload         19
     672: getfield      #142                // Field mindustry/gen/Unit.id:I
     675: invokevirtual #19                 // Method arc/util/io/Writes.i:(I)V
     678: goto          1016
     681: aload_1
     682: instanceof    #144                // class mindustry/io/TypeIO$UnitBox
     685: ifeq          712
     688: aload_1
     689: checkcast     #144                // class mindustry/io/TypeIO$UnitBox
     692: astore        20
     694: aload_0
     695: bipush        17
     697: invokevirtual #7                  // Method arc/util/io/Writes.b:(I)V
     700: aload_0
     701: aload         20
     703: getfield      #146                // Field mindustry/io/TypeIO$UnitBox.id:I
     706: invokevirtual #19                 // Method arc/util/io/Writes.i:(I)V
     709: goto          1016
     712: aload_1
     713: instanceof    #147                // class "[Larc/math/geom/Vec2;"
     716: ifeq          791
     719: aload_1
     720: checkcast     #147                // class "[Larc/math/geom/Vec2;"
     723: astore        21
     725: aload_0
     726: bipush        18
     728: invokevirtual #7                  // Method arc/util/io/Writes.b:(I)V
     731: aload_0
     732: aload         21
     734: arraylength
     735: invokevirtual #65                 // Method arc/util/io/Writes.s:(I)V
     738: aload         21
     740: astore        26
     742: aload         26
     744: arraylength
     745: istore        27
     747: iconst_0
     748: istore        28
     750: iload         28
     752: iload         27
     754: if_icmpge     788
     757: aload         26
     759: iload         28
     761: aaload
     762: astore        29
     764: aload_0
     765: aload         29
     767: getfield      #149                // Field arc/math/geom/Vec2.x:F
     770: invokevirtual #38                 // Method arc/util/io/Writes.f:(F)V
     773: aload_0
     774: aload         29
     776: getfield      #154                // Field arc/math/geom/Vec2.y:F
     779: invokevirtual #38                 // Method arc/util/io/Writes.f:(F)V
     782: iinc          28, 1
     785: goto          750
     788: goto          1016
     791: aload_1
     792: instanceof    #150                // class arc/math/geom/Vec2
     795: ifeq          831
     798: aload_1
     799: checkcast     #150                // class arc/math/geom/Vec2
     802: astore        22
     804: aload_0
     805: bipush        19
     807: invokevirtual #7                  // Method arc/util/io/Writes.b:(I)V
     810: aload_0
     811: aload         22
     813: getfield      #149                // Field arc/math/geom/Vec2.x:F
     816: invokevirtual #38                 // Method arc/util/io/Writes.f:(F)V
     819: aload_0
     820: aload         22
     822: getfield      #154                // Field arc/math/geom/Vec2.y:F
     825: invokevirtual #38                 // Method arc/util/io/Writes.f:(F)V
     828: goto          1016
     831: aload_1
     832: instanceof    #156                // class mindustry/game/Team
     835: ifeq          862
     838: aload_1
     839: checkcast     #156                // class mindustry/game/Team
     842: astore        23
     844: aload_0
     845: bipush        20
     847: invokevirtual #7                  // Method arc/util/io/Writes.b:(I)V
     850: aload_0
     851: aload         23
     853: getfield      #158                // Field mindustry/game/Team.id:I
     856: invokevirtual #7                  // Method arc/util/io/Writes.b:(I)V
     859: goto          1016
     862: aload_1
     863: instanceof    #159                // class "[I"
     866: ifeq          890
     869: aload_1
     870: checkcast     #159                // class "[I"
     873: astore        24
     875: aload_0
     876: bipush        21
     878: invokevirtual #7                  // Method arc/util/io/Writes.b:(I)V
     881: aload_0
     882: aload         24
     884: invokestatic  #160                // Method writeInts:(Larc/util/io/Writes;[I)V
     887: goto          1016
     890: aload_1
     891: instanceof    #164                // class "[Ljava/lang/Object;"
     894: ifeq          957
     897: aload_1
     898: checkcast     #164                // class "[Ljava/lang/Object;"
     901: astore        25
     903: aload_0
     904: bipush        22
     906: invokevirtual #7                  // Method arc/util/io/Writes.b:(I)V
     909: aload_0
     910: aload         25
     912: arraylength
     913: invokevirtual #19                 // Method arc/util/io/Writes.i:(I)V
     916: aload         25
     918: astore        26
     920: aload         26
     922: arraylength
     923: istore        27
     925: iconst_0
     926: istore        28
     928: iload         28
     930: iload         27
     932: if_icmpge     954
     935: aload         26
     937: iload         28
     939: aaload
     940: astore        29
     942: aload_0
     943: aload         29
     945: invokestatic  #166                // Method writeObject:(Larc/util/io/Writes;Ljava/lang/Object;)V
     948: iinc          28, 1
     951: goto          928
     954: goto          1016
     957: aload_1
     958: instanceof    #170                // class mindustry/ai/UnitCommand
     961: ifeq          986
     964: aload_1
     965: checkcast     #170                // class mindustry/ai/UnitCommand
     968: astore_2
     969: aload_0
     970: bipush        23
     972: invokevirtual #7                  // Method arc/util/io/Writes.b:(I)V
     975: aload_0
     976: aload_2
     977: getfield      #172                // Field mindustry/ai/UnitCommand.id:S
     980: invokevirtual #65                 // Method arc/util/io/Writes.s:(I)V
     983: goto          1016
     986: new           #173                // class java/lang/IllegalArgumentException
     989: dup
     990: new           #175                // class java/lang/StringBuilder
     993: dup
     994: invokespecial #177                // Method java/lang/StringBuilder."<init>":()V
     997: ldc           #178                // String Unknown object type:
     999: invokevirtual #180                // Method java/lang/StringBuilder.append:(Ljava/lang/String;)Ljava/lang/StringBuilder;
    1002: aload_1
    1003: invokevirtual #184                // Method java/lang/Object.getClass:()Ljava/lang/Class;
    1006: invokevirtual #188                // Method java/lang/StringBuilder.append:(Ljava/lang/Object;)Ljava/lang/StringBuilder;
    1009: invokevirtual #191                // Method java/lang/StringBuilder.toString:()Ljava/lang/String;
    1012: invokespecial #195                // Method java/lang/IllegalArgumentException."<init>":(Ljava/lang/String;)V
    1015: athrow
    1016: return

  public static java.lang.Object readObject(arc.util.io.Reads);
    Code:
       0: aload_0
       1: iconst_0
       2: invokestatic  #198                // Method readObjectBoxed:(Larc/util/io/Reads;Z)Ljava/lang/Object;
       5: areturn

  public static java.lang.Object readObjectBoxed(arc.util.io.Reads, boolean);
    Code:
       0: aload_0
       1: iload_1
       2: aconst_null
       3: invokestatic  #202                // Method readObject:(Larc/util/io/Reads;ZLmindustry/io/TypeIO$ContentMapper;)Ljava/lang/Object;
       6: areturn

  public static java.lang.Object readObject(arc.util.io.Reads, boolean, mindustry.io.TypeIO$ContentMapper);
    Code:
       0: aload_0
       1: invokevirtual #206                // Method arc/util/io/Reads.b:()B
       4: istore_3
       5: iload_3
       6: tableswitch   { // 0 to 23
                     0: 116
                     1: 120
                     2: 130
                     3: 140
                     4: 150
                     5: 157
                     6: 203
                     7: 250
                     8: 268
                     9: 314
                    10: 341
                    11: 351
                    12: 361
                    13: 392
                    14: 403
                    15: 427
                    16: 436
                    17: 478
                    18: 509
                    19: 563
                    20: 581
                    21: 592
                    22: 599
                    23: 644
               default: 657
          }
     116: aconst_null
     117: goto          684
     120: aload_0
     121: invokevirtual #211                // Method arc/util/io/Reads.i:()I
     124: invokestatic  #213                // Method java/lang/Integer.valueOf:(I)Ljava/lang/Integer;
     127: goto          684
     130: aload_0
     131: invokevirtual #217                // Method arc/util/io/Reads.l:()J
     134: invokestatic  #219                // Method java/lang/Long.valueOf:(J)Ljava/lang/Long;
     137: goto          684
     140: aload_0
     141: invokevirtual #222                // Method arc/util/io/Reads.f:()F
     144: invokestatic  #224                // Method java/lang/Float.valueOf:(F)Ljava/lang/Float;
     147: goto          684
     150: aload_0
     151: invokestatic  #227                // Method readString:(Larc/util/io/Reads;)Ljava/lang/String;
     154: goto          684
     157: aload_2
     158: ifnonnull     182
     161: getstatic     #231                // Field mindustry/Vars.content:Lmindustry/core/ContentLoader;
     164: getstatic     #236                // Field mindustry/ctype/ContentType.all:[Lmindustry/ctype/ContentType;
     167: aload_0
     168: invokevirtual #206                // Method arc/util/io/Reads.b:()B
     171: aaload
     172: aload_0
     173: invokevirtual #240                // Method arc/util/io/Reads.s:()S
     176: invokevirtual #243                // Method mindustry/core/ContentLoader.getByID:(Lmindustry/ctype/ContentType;I)Lmindustry/ctype/Content;
     179: goto          684
     182: aload_2
     183: getstatic     #236                // Field mindustry/ctype/ContentType.all:[Lmindustry/ctype/ContentType;
     186: aload_0
     187: invokevirtual #206                // Method arc/util/io/Reads.b:()B
     190: aaload
     191: aload_0
     192: invokevirtual #240                // Method arc/util/io/Reads.s:()S
     195: invokeinterface #249,  3          // InterfaceMethod mindustry/io/TypeIO$ContentMapper.get:(Lmindustry/ctype/ContentType;I)Lmindustry/ctype/Content;
     200: goto          684
     203: aload_0
     204: invokevirtual #240                // Method arc/util/io/Reads.s:()S
     207: istore        4
     209: new           #68                 // class arc/struct/IntSeq
     212: dup
     213: iload         4
     215: invokespecial #254                // Method arc/struct/IntSeq."<init>":(I)V
     218: astore        5
     220: iconst_0
     221: istore        6
     223: iload         6
     225: iload         4
     227: if_icmpge     245
     230: aload         5
     232: aload_0
     233: invokevirtual #211                // Method arc/util/io/Reads.i:()I
     236: invokevirtual #256                // Method arc/struct/IntSeq.add:(I)V
     239: iinc          6, 1
     242: goto          223
     245: aload         5
     247: goto          684
     250: new           #78                 // class arc/math/geom/Point2
     253: dup
     254: aload_0
     255: invokevirtual #211                // Method arc/util/io/Reads.i:()I
     258: aload_0
     259: invokevirtual #211                // Method arc/util/io/Reads.i:()I
     262: invokespecial #259                // Method arc/math/geom/Point2."<init>":(II)V
     265: goto          684
     268: aload_0
     269: invokevirtual #206                // Method arc/util/io/Reads.b:()B
     272: istore        4
     274: iload         4
     276: anewarray     #78                 // class arc/math/geom/Point2
     279: astore        5
     281: iconst_0
     282: istore        6
     284: iload         6
     286: iload         4
     288: if_icmpge     309
     291: aload         5
     293: iload         6
     295: aload_0
     296: invokevirtual #211                // Method arc/util/io/Reads.i:()I
     299: invokestatic  #262                // Method arc/math/geom/Point2.unpack:(I)Larc/math/geom/Point2;
     302: aastore
     303: iinc          6, 1
     306: goto          284
     309: aload         5
     311: goto          684
     314: getstatic     #231                // Field mindustry/Vars.content:Lmindustry/core/ContentLoader;
     317: getstatic     #236                // Field mindustry/ctype/ContentType.all:[Lmindustry/ctype/ContentType;
     320: aload_0
     321: invokevirtual #206                // Method arc/util/io/Reads.b:()B
     324: aaload
     325: aload_0
     326: invokevirtual #240                // Method arc/util/io/Reads.s:()S
     329: invokevirtual #243                // Method mindustry/core/ContentLoader.getByID:(Lmindustry/ctype/ContentType;I)Lmindustry/ctype/Content;
     332: checkcast     #98                 // class mindustry/ctype/UnlockableContent
     335: getfield      #266                // Field mindustry/ctype/UnlockableContent.techNode:Lmindustry/content/TechTree$TechNode;
     338: goto          684
     341: aload_0
     342: invokevirtual #270                // Method arc/util/io/Reads.bool:()Z
     345: invokestatic  #272                // Method java/lang/Boolean.valueOf:(Z)Ljava/lang/Boolean;
     348: goto          684
     351: aload_0
     352: invokevirtual #275                // Method arc/util/io/Reads.d:()D
     355: invokestatic  #277                // Method java/lang/Double.valueOf:(D)Ljava/lang/Double;
     358: goto          684
     361: iload_1
     362: ifne          378
     365: getstatic     #280                // Field mindustry/Vars.world:Lmindustry/core/World;
     368: aload_0
     369: invokevirtual #211                // Method arc/util/io/Reads.i:()I
     372: invokevirtual #284                // Method mindustry/core/World.build:(I)Lmindustry/gen/Building;
     375: goto          684
     378: new           #126                // class mindustry/io/TypeIO$BuildingBox
     381: dup
     382: aload_0
     383: invokevirtual #211                // Method arc/util/io/Reads.i:()I
     386: invokespecial #290                // Method mindustry/io/TypeIO$BuildingBox."<init>":(I)V
     389: goto          684
     392: getstatic     #291                // Field mindustry/logic/LAccess.all:[Lmindustry/logic/LAccess;
     395: aload_0
     396: invokevirtual #240                // Method arc/util/io/Reads.s:()S
     399: aaload
     400: goto          684
     403: aload_0
     404: invokevirtual #211                // Method arc/util/io/Reads.i:()I
     407: istore        4
     409: iload         4
     411: newarray       byte
     413: astore        5
     415: aload_0
     416: aload         5
     418: invokevirtual #294                // Method arc/util/io/Reads.b:([B)[B
     421: pop
     422: aload         5
     424: goto          684
     427: aload_0
     428: invokevirtual #206                // Method arc/util/io/Reads.b:()B
     431: pop
     432: aconst_null
     433: goto          684
     436: aload_0
     437: invokevirtual #211                // Method arc/util/io/Reads.i:()I
     440: istore        4
     442: iload         4
     444: newarray       boolean
     446: astore        5
     448: iconst_0
     449: istore        6
     451: iload         6
     453: iload         4
     455: if_icmpge     473
     458: aload         5
     460: iload         6
     462: aload_0
     463: invokevirtual #270                // Method arc/util/io/Reads.bool:()Z
     466: bastore
     467: iinc          6, 1
     470: goto          451
     473: aload         5
     475: goto          684
     478: iload_1
     479: ifne          495
     482: getstatic     #297                // Field mindustry/gen/Groups.unit:Lmindustry/entities/EntityGroup;
     485: aload_0
     486: invokevirtual #211                // Method arc/util/io/Reads.i:()I
     489: invokevirtual #303                // Method mindustry/entities/EntityGroup.getByID:(I)Lmindustry/gen/Entityc;
     492: goto          684
     495: new           #144                // class mindustry/io/TypeIO$UnitBox
     498: dup
     499: aload_0
     500: invokevirtual #211                // Method arc/util/io/Reads.i:()I
     503: invokespecial #308                // Method mindustry/io/TypeIO$UnitBox."<init>":(I)V
     506: goto          684
     509: aload_0
     510: invokevirtual #240                // Method arc/util/io/Reads.s:()S
     513: istore        4
     515: iload         4
     517: anewarray     #150                // class arc/math/geom/Vec2
     520: astore        5
     522: iconst_0
     523: istore        6
     525: iload         6
     527: iload         4
     529: if_icmpge     558
     532: aload         5
     534: iload         6
     536: new           #150                // class arc/math/geom/Vec2
     539: dup
     540: aload_0
     541: invokevirtual #222                // Method arc/util/io/Reads.f:()F
     544: aload_0
     545: invokevirtual #222                // Method arc/util/io/Reads.f:()F
     548: invokespecial #309                // Method arc/math/geom/Vec2."<init>":(FF)V
     551: aastore
     552: iinc          6, 1
     555: goto          525
     558: aload         5
     560: goto          684
     563: new           #150                // class arc/math/geom/Vec2
     566: dup
     567: aload_0
     568: invokevirtual #222                // Method arc/util/io/Reads.f:()F
     571: aload_0
     572: invokevirtual #222                // Method arc/util/io/Reads.f:()F
     575: invokespecial #309                // Method arc/math/geom/Vec2."<init>":(FF)V
     578: goto          684
     581: getstatic     #312                // Field mindustry/game/Team.all:[Lmindustry/game/Team;
     584: aload_0
     585: invokevirtual #315                // Method arc/util/io/Reads.ub:()I
     588: aaload
     589: goto          684
     592: aload_0
     593: invokestatic  #318                // Method readInts:(Larc/util/io/Reads;)[I
     596: goto          684
     599: aload_0
     600: invokevirtual #211                // Method arc/util/io/Reads.i:()I
     603: istore        4
     605: iload         4
     607: anewarray     #2                  // class java/lang/Object
     610: astore        5
     612: iconst_0
     613: istore        6
     615: iload         6
     617: iload         4
     619: if_icmpge     639
     622: aload         5
     624: iload         6
     626: aload_0
     627: iload_1
     628: aload_2
     629: invokestatic  #202                // Method readObject:(Larc/util/io/Reads;ZLmindustry/io/TypeIO$ContentMapper;)Ljava/lang/Object;
     632: aastore
     633: iinc          6, 1
     636: goto          615
     639: aload         5
     641: goto          684
     644: getstatic     #231                // Field mindustry/Vars.content:Lmindustry/core/ContentLoader;
     647: aload_0
     648: invokevirtual #322                // Method arc/util/io/Reads.us:()I
     651: invokevirtual #325                // Method mindustry/core/ContentLoader.unitCommand:(I)Lmindustry/ai/UnitCommand;
     654: goto          684
     657: new           #173                // class java/lang/IllegalArgumentException
     660: dup
     661: new           #175                // class java/lang/StringBuilder
     664: dup
     665: invokespecial #177                // Method java/lang/StringBuilder."<init>":()V
     668: ldc           #178                // String Unknown object type:
     670: invokevirtual #180                // Method java/lang/StringBuilder.append:(Ljava/lang/String;)Ljava/lang/StringBuilder;
     673: iload_3
     674: invokevirtual #329                // Method java/lang/StringBuilder.append:(I)Ljava/lang/StringBuilder;
     677: invokevirtual #191                // Method java/lang/StringBuilder.toString:()Ljava/lang/String;
     680: invokespecial #195                // Method java/lang/IllegalArgumentException."<init>":(Ljava/lang/String;)V
     683: athrow
     684: areturn

  public static void writePayload(arc.util.io.Writes, mindustry.world.blocks.payloads.Payload);
    Code:
       0: aload_1
       1: aload_0
       2: invokestatic  #332                // InterfaceMethod mindustry/world/blocks/payloads/Payload.write:(Lmindustry/world/blocks/payloads/Payload;Larc/util/io/Writes;)V
       5: return

  public static mindustry.world.blocks.payloads.Payload readPayload(arc.util.io.Reads);
    Code:
       0: aload_0
       1: invokestatic  #338                // InterfaceMethod mindustry/world/blocks/payloads/Payload.read:(Larc/util/io/Reads;)Lmindustry/world/blocks/payloads/Payload;
       4: areturn

  public static void writeMounts(arc.util.io.Writes, mindustry.entities.units.WeaponMount[]);
    Code:
       0: aload_0
       1: aload_1
       2: arraylength
       3: invokevirtual #7                  // Method arc/util/io/Writes.b:(I)V
       6: aload_1
       7: astore_2
       8: aload_2
       9: arraylength
      10: istore_3
      11: iconst_0
      12: istore        4
      14: iload         4
      16: iload_3
      17: if_icmpge     81
      20: aload_2
      21: iload         4
      23: aaload
      24: astore        5
      26: aload_0
      27: aload         5
      29: getfield      #342                // Field mindustry/entities/units/WeaponMount.shoot:Z
      32: ifeq          39
      35: iconst_1
      36: goto          40
      39: iconst_0
      40: aload         5
      42: getfield      #348                // Field mindustry/entities/units/WeaponMount.rotate:Z
      45: ifeq          52
      48: iconst_2
      49: goto          53
      52: iconst_0
      53: ior
      54: invokevirtual #7                  // Method arc/util/io/Writes.b:(I)V
      57: aload_0
      58: aload         5
      60: getfield      #351                // Field mindustry/entities/units/WeaponMount.aimX:F
      63: invokevirtual #38                 // Method arc/util/io/Writes.f:(F)V
      66: aload_0
      67: aload         5
      69: getfield      #354                // Field mindustry/entities/units/WeaponMount.aimY:F
      72: invokevirtual #38                 // Method arc/util/io/Writes.f:(F)V
      75: iinc          4, 1
      78: goto          14
      81: return

  public static mindustry.entities.units.WeaponMount[] readMounts(arc.util.io.Reads, mindustry.entities.units.WeaponMount[]);
    Code:
       0: aload_0
       1: invokevirtual #206                // Method arc/util/io/Reads.b:()B
       4: istore_2
       5: iconst_0
       6: istore_3
       7: iload_3
       8: iload_2
       9: if_icmpge     97
      12: aload_0
      13: invokevirtual #206                // Method arc/util/io/Reads.b:()B
      16: istore        4
      18: aload_0
      19: invokevirtual #222                // Method arc/util/io/Reads.f:()F
      22: fstore        5
      24: aload_0
      25: invokevirtual #222                // Method arc/util/io/Reads.f:()F
      28: fstore        6
      30: iload_3
      31: aload_1
      32: arraylength
      33: iconst_1
      34: isub
      35: if_icmpgt     91
      38: aload_1
      39: iload_3
      40: aaload
      41: astore        7
      43: aload         7
      45: fload         5
      47: putfield      #351                // Field mindustry/entities/units/WeaponMount.aimX:F
      50: aload         7
      52: fload         6
      54: putfield      #354                // Field mindustry/entities/units/WeaponMount.aimY:F
      57: aload         7
      59: iload         4
      61: iconst_1
      62: iand
      63: ifeq          70
      66: iconst_1
      67: goto          71
      70: iconst_0
      71: putfield      #342                // Field mindustry/entities/units/WeaponMount.shoot:Z
      74: aload         7
      76: iload         4
      78: iconst_2
      79: iand
      80: ifeq          87
      83: iconst_1
      84: goto          88
      87: iconst_0
      88: putfield      #348                // Field mindustry/entities/units/WeaponMount.rotate:Z
      91: iinc          3, 1
      94: goto          7
      97: aload_1
      98: areturn

  public static mindustry.entities.units.WeaponMount[] readMounts(arc.util.io.Reads);
    Code:
       0: aload_0
       1: aload_0
       2: invokevirtual #206                // Method arc/util/io/Reads.b:()B
       5: bipush        9
       7: imul
       8: invokevirtual #357                // Method arc/util/io/Reads.skip:(I)V
      11: getstatic     #360                // Field noMounts:[Lmindustry/entities/units/WeaponMount;
      14: areturn

  public static mindustry.entities.abilities.Ability[] readAbilities(arc.util.io.Reads, mindustry.entities.abilities.Ability[]);
    Code:
       0: aload_0
       1: invokevirtual #206                // Method arc/util/io/Reads.b:()B
       4: istore_2
       5: iconst_0
       6: istore_3
       7: iload_3
       8: iload_2
       9: if_icmpge     38
      12: aload_0
      13: invokevirtual #222                // Method arc/util/io/Reads.f:()F
      16: fstore        4
      18: aload_1
      19: arraylength
      20: iload_3
      21: if_icmple     32
      24: aload_1
      25: iload_3
      26: aaload
      27: fload         4
      29: putfield      #364                // Field mindustry/entities/abilities/Ability.data:F
      32: iinc          3, 1
      35: goto          7
      38: aload_1
      39: areturn

  public static void writeAbilities(arc.util.io.Writes, mindustry.entities.abilities.Ability[]);
    Code:
       0: aload_0
       1: aload_1
       2: arraylength
       3: invokevirtual #7                  // Method arc/util/io/Writes.b:(I)V
       6: aload_1
       7: astore_2
       8: aload_2
       9: arraylength
      10: istore_3
      11: iconst_0
      12: istore        4
      14: iload         4
      16: iload_3
      17: if_icmpge     41
      20: aload_2
      21: iload         4
      23: aaload
      24: astore        5
      26: aload_0
      27: aload         5
      29: getfield      #364                // Field mindustry/entities/abilities/Ability.data:F
      32: invokevirtual #38                 // Method arc/util/io/Writes.f:(F)V
      35: iinc          4, 1
      38: goto          14
      41: return

  public static mindustry.entities.abilities.Ability[] readAbilities(arc.util.io.Reads);
    Code:
       0: aload_0
       1: aload_0
       2: invokevirtual #206                // Method arc/util/io/Reads.b:()B
       5: invokevirtual #357                // Method arc/util/io/Reads.skip:(I)V
       8: getstatic     #369                // Field noAbilities:[Lmindustry/entities/abilities/Ability;
      11: areturn

  public static void writeUnitContainer(arc.util.io.Writes, mindustry.entities.Units$UnitSyncContainer);
    Code:
       0: aload_0
       1: aload_1
       2: getfield      #373                // Field mindustry/entities/Units$UnitSyncContainer.unit:Lmindustry/gen/Unit;
       5: getfield      #142                // Field mindustry/gen/Unit.id:I
       8: invokevirtual #19                 // Method arc/util/io/Writes.i:(I)V
      11: aload_0
      12: aload_1
      13: getfield      #373                // Field mindustry/entities/Units$UnitSyncContainer.unit:Lmindustry/gen/Unit;
      16: invokevirtual #378                // Method mindustry/gen/Unit.classId:()I
      19: sipush        255
      22: iand
      23: invokevirtual #7                  // Method arc/util/io/Writes.b:(I)V
      26: aload_1
      27: getfield      #373                // Field mindustry/entities/Units$UnitSyncContainer.unit:Lmindustry/gen/Unit;
      30: invokevirtual #381                // Method mindustry/gen/Unit.beforeWrite:()V
      33: aload_1
      34: getfield      #373                // Field mindustry/entities/Units$UnitSyncContainer.unit:Lmindustry/gen/Unit;
      37: aload_0
      38: invokevirtual #384                // Method mindustry/gen/Unit.writeSync:(Larc/util/io/Writes;)V
      41: return

  public static mindustry.entities.Units$UnitSyncContainer readUnitContainer(arc.util.io.Reads);
    Code:
       0: aload_0
       1: invokevirtual #211                // Method arc/util/io/Reads.i:()I
       4: istore_1
       5: aload_0
       6: invokevirtual #315                // Method arc/util/io/Reads.ub:()I
       9: istore_2
      10: getstatic     #297                // Field mindustry/gen/Groups.unit:Lmindustry/entities/EntityGroup;
      13: iload_1
      14: invokevirtual #303                // Method mindustry/entities/EntityGroup.getByID:(I)Lmindustry/gen/Entityc;
      17: checkcast     #140                // class mindustry/gen/Unit
      20: astore_3
      21: iconst_0
      22: istore        4
      24: iconst_0
      25: istore        5
      27: aload_3
      28: ifnonnull     72
      31: iload_2
      32: sipush        255
      35: iand
      36: invokestatic  #388                // Method mindustry/gen/EntityMapping.map:(I)Larc/func/Prov;
      39: invokeinterface #394,  1          // InterfaceMethod arc/func/Prov.get:()Ljava/lang/Object;
      44: checkcast     #140                // class mindustry/gen/Unit
      47: astore_3
      48: aload_3
      49: iload_1
      50: invokevirtual #399                // Method mindustry/gen/Unit.id:(I)V
      53: getstatic     #401                // Field mindustry/Vars.netClient:Lmindustry/core/NetClient;
      56: aload_3
      57: invokevirtual #405                // Method mindustry/gen/Unit.id:()I
      60: invokevirtual #407                // Method mindustry/core/NetClient.isEntityUsed:(I)Z
      63: ifne          69
      66: iconst_1
      67: istore        4
      69: iconst_1
      70: istore        5
      72: aload_3
      73: aload_0
      74: invokevirtual #413                // Method mindustry/gen/Unit.readSync:(Larc/util/io/Reads;)V
      77: iload         5
      79: ifeq          86
      82: aload_3
      83: invokevirtual #417                // Method mindustry/gen/Unit.snapSync:()V
      86: iload         4
      88: ifeq          105
      91: aload_3
      92: invokevirtual #420                // Method mindustry/gen/Unit.add:()V
      95: getstatic     #401                // Field mindustry/Vars.netClient:Lmindustry/core/NetClient;
      98: aload_3
      99: invokevirtual #405                // Method mindustry/gen/Unit.id:()I
     102: invokevirtual #422                // Method mindustry/core/NetClient.addRemovedEntity:(I)V
     105: aconst_null
     106: areturn

  public static void writeUnit(arc.util.io.Writes, mindustry.gen.Unit);
    Code:
       0: aload_0
       1: aload_1
       2: ifnonnull     9
       5: iconst_0
       6: goto          21
       9: aload_1
      10: instanceof    #425                // class mindustry/gen/BlockUnitc
      13: ifeq          20
      16: iconst_1
      17: goto          21
      20: iconst_2
      21: invokevirtual #7                  // Method arc/util/io/Writes.b:(I)V
      24: aload_1
      25: instanceof    #425                // class mindustry/gen/BlockUnitc
      28: ifeq          50
      31: aload_0
      32: aload_1
      33: checkcast     #425                // class mindustry/gen/BlockUnitc
      36: invokeinterface #427,  1          // InterfaceMethod mindustry/gen/BlockUnitc.tile:()Lmindustry/gen/Building;
      41: invokevirtual #123                // Method mindustry/gen/Building.pos:()I
      44: invokevirtual #19                 // Method arc/util/io/Writes.i:(I)V
      47: goto          70
      50: aload_1
      51: ifnonnull     62
      54: aload_0
      55: iconst_0
      56: invokevirtual #19                 // Method arc/util/io/Writes.i:(I)V
      59: goto          70
      62: aload_0
      63: aload_1
      64: getfield      #142                // Field mindustry/gen/Unit.id:I
      67: invokevirtual #19                 // Method arc/util/io/Writes.i:(I)V
      70: return

  public static mindustry.gen.Unit readUnit(arc.util.io.Reads);
    Code:
       0: aload_0
       1: invokevirtual #206                // Method arc/util/io/Reads.b:()B
       4: istore_1
       5: aload_0
       6: invokevirtual #211                // Method arc/util/io/Reads.i:()I
       9: istore_2
      10: iload_1
      11: ifne          16
      14: aconst_null
      15: areturn
      16: iload_1
      17: iconst_2
      18: if_icmpne     32
      21: getstatic     #297                // Field mindustry/gen/Groups.unit:Lmindustry/entities/EntityGroup;
      24: iload_2
      25: invokevirtual #303                // Method mindustry/entities/EntityGroup.getByID:(I)Lmindustry/gen/Entityc;
      28: checkcast     #140                // class mindustry/gen/Unit
      31: areturn
      32: iload_1
      33: iconst_1
      34: if_icmpne     70
      37: getstatic     #280                // Field mindustry/Vars.world:Lmindustry/core/World;
      40: iload_2
      41: invokevirtual #284                // Method mindustry/core/World.build:(I)Lmindustry/gen/Building;
      44: astore_3
      45: aload_3
      46: instanceof    #431                // class mindustry/world/blocks/ControlBlock
      49: ifeq          68
      52: aload_3
      53: checkcast     #431                // class mindustry/world/blocks/ControlBlock
      56: astore        4
      58: aload         4
      60: invokeinterface #433,  1          // InterfaceMethod mindustry/world/blocks/ControlBlock.unit:()Lmindustry/gen/Unit;
      65: goto          69
      68: aconst_null
      69: areturn
      70: aconst_null
      71: areturn

  public static void writeCommand(arc.util.io.Writes, mindustry.ai.UnitCommand);
    Code:
       0: aload_0
       1: aload_1
       2: ifnonnull     11
       5: sipush        255
       8: goto          15
      11: aload_1
      12: getfield      #172                // Field mindustry/ai/UnitCommand.id:S
      15: invokevirtual #7                  // Method arc/util/io/Writes.b:(I)V
      18: return

  public static mindustry.ai.UnitCommand readCommand(arc.util.io.Reads);
    Code:
       0: aload_0
       1: invokevirtual #315                // Method arc/util/io/Reads.ub:()I
       4: istore_1
       5: iload_1
       6: sipush        255
       9: if_icmpne     16
      12: aconst_null
      13: goto          23
      16: getstatic     #231                // Field mindustry/Vars.content:Lmindustry/core/ContentLoader;
      19: iload_1
      20: invokevirtual #325                // Method mindustry/core/ContentLoader.unitCommand:(I)Lmindustry/ai/UnitCommand;
      23: areturn

  public static void writeStance(arc.util.io.Writes, mindustry.ai.UnitStance);
    Code:
       0: aload_0
       1: aload_1
       2: ifnonnull     11
       5: sipush        255
       8: goto          15
      11: aload_1
      12: getfield      #436                // Field mindustry/ai/UnitStance.id:S
      15: invokevirtual #7                  // Method arc/util/io/Writes.b:(I)V
      18: return

  public static mindustry.ai.UnitStance readStance(arc.util.io.Reads);
    Code:
       0: aload_0
       1: invokevirtual #315                // Method arc/util/io/Reads.ub:()I
       4: istore_1
       5: iload_1
       6: sipush        255
       9: if_icmpeq     25
      12: iload_1
      13: getstatic     #231                // Field mindustry/Vars.content:Lmindustry/core/ContentLoader;
      16: invokevirtual #439                // Method mindustry/core/ContentLoader.unitStances:()Larc/struct/Seq;
      19: getfield      #443                // Field arc/struct/Seq.size:I
      22: if_icmplt     31
      25: getstatic     #446                // Field mindustry/ai/UnitStance.stop:Lmindustry/ai/UnitStance;
      28: goto          38
      31: getstatic     #231                // Field mindustry/Vars.content:Lmindustry/core/ContentLoader;
      34: iload_1
      35: invokevirtual #450                // Method mindustry/core/ContentLoader.unitStance:(I)Lmindustry/ai/UnitStance;
      38: areturn

  public static void writeEntity(arc.util.io.Writes, mindustry.gen.Entityc);
    Code:
       0: aload_0
       1: aload_1
       2: ifnonnull     9
       5: iconst_m1
       6: goto          15
       9: aload_1
      10: invokeinterface #454,  1          // InterfaceMethod mindustry/gen/Entityc.id:()I
      15: invokevirtual #19                 // Method arc/util/io/Writes.i:(I)V
      18: return

  public static <T extends mindustry.gen.Entityc> T readEntity(arc.util.io.Reads);
    Code:
       0: getstatic     #457                // Field mindustry/gen/Groups.sync:Lmindustry/entities/EntityGroup;
       3: aload_0
       4: invokevirtual #211                // Method arc/util/io/Reads.i:()I
       7: invokevirtual #303                // Method mindustry/entities/EntityGroup.getByID:(I)Lmindustry/gen/Entityc;
      10: areturn

  public static void writeBuilding(arc.util.io.Writes, mindustry.gen.Building);
    Code:
       0: aload_0
       1: aload_1
       2: ifnonnull     9
       5: iconst_m1
       6: goto          13
       9: aload_1
      10: invokevirtual #123                // Method mindustry/gen/Building.pos:()I
      13: invokevirtual #19                 // Method arc/util/io/Writes.i:(I)V
      16: return

  public static mindustry.gen.Building readBuilding(arc.util.io.Reads);
    Code:
       0: getstatic     #280                // Field mindustry/Vars.world:Lmindustry/core/World;
       3: aload_0
       4: invokevirtual #211                // Method arc/util/io/Reads.i:()I
       7: invokevirtual #284                // Method mindustry/core/World.build:(I)Lmindustry/gen/Building;
      10: areturn

  public static void writeTile(arc.util.io.Writes, mindustry.world.Tile);
    Code:
       0: aload_0
       1: aload_1
       2: ifnonnull     13
       5: iconst_m1
       6: iconst_m1
       7: invokestatic  #460                // Method arc/math/geom/Point2.pack:(II)I
      10: goto          17
      13: aload_1
      14: invokevirtual #463                // Method mindustry/world/Tile.pos:()I
      17: invokevirtual #19                 // Method arc/util/io/Writes.i:(I)V
      20: return

  public static mindustry.world.Tile readTile(arc.util.io.Reads);
    Code:
       0: getstatic     #280                // Field mindustry/Vars.world:Lmindustry/core/World;
       3: aload_0
       4: invokevirtual #211                // Method arc/util/io/Reads.i:()I
       7: invokevirtual #466                // Method mindustry/core/World.tile:(I)Lmindustry/world/Tile;
      10: areturn

  public static void writeBlock(arc.util.io.Writes, mindustry.world.Block);
    Code:
       0: aload_0
       1: aload_1
       2: ifnonnull     9
       5: iconst_m1
       6: goto          13
       9: aload_1
      10: getfield      #469                // Field mindustry/world/Block.id:S
      13: invokevirtual #65                 // Method arc/util/io/Writes.s:(I)V
      16: return

  public static mindustry.world.Block readBlock(arc.util.io.Reads);
    Code:
       0: aload_0
       1: invokevirtual #240                // Method arc/util/io/Reads.s:()S
       4: istore_1
       5: iload_1
       6: iconst_m1
       7: if_icmpne     14
      10: aconst_null
      11: goto          21
      14: getstatic     #231                // Field mindustry/Vars.content:Lmindustry/core/ContentLoader;
      17: iload_1
      18: invokevirtual #472                // Method mindustry/core/ContentLoader.block:(I)Lmindustry/world/Block;
      21: areturn

  public static int getMaxPlans(arc.struct.Queue<mindustry.entities.units.BuildPlan>);
    Code:
       0: aload_0
       1: getfield      #476                // Field arc/struct/Queue.size:I
       4: bipush        20
       6: invokestatic  #479                // Method java/lang/Math.min:(II)I
       9: istore_1
      10: iconst_0
      11: istore_2
      12: iconst_0
      13: istore_3
      14: iload_3
      15: iload_1
      16: if_icmpge     107
      19: aload_0
      20: iload_3
      21: invokevirtual #484                // Method arc/struct/Queue.get:(I)Ljava/lang/Object;
      24: checkcast     #487                // class mindustry/entities/units/BuildPlan
      27: astore        4
      29: aload         4
      31: getfield      #489                // Field mindustry/entities/units/BuildPlan.config:Ljava/lang/Object;
      34: astore        6
      36: aload         6
      38: instanceof    #133                // class "[B"
      41: ifeq          57
      44: aload         6
      46: checkcast     #133                // class "[B"
      49: astore        5
      51: iload_2
      52: aload         5
      54: arraylength
      55: iadd
      56: istore_2
      57: aload         4
      59: getfield      #489                // Field mindustry/entities/units/BuildPlan.config:Ljava/lang/Object;
      62: astore        6
      64: aload         6
      66: instanceof    #42                 // class java/lang/String
      69: ifeq          87
      72: aload         6
      74: checkcast     #42                 // class java/lang/String
      77: astore        5
      79: iload_2
      80: aload         5
      82: invokevirtual #493                // Method java/lang/String.length:()I
      85: iadd
      86: istore_2
      87: iload_2
      88: sipush        500
      91: if_icmple     101
      94: iload_3
      95: iconst_1
      96: iadd
      97: istore_1
      98: goto          107
     101: iinc          3, 1
     104: goto          14
     107: iload_1
     108: ireturn

  public static void writePlansQueueNet(arc.util.io.Writes, arc.struct.Queue<mindustry.entities.units.BuildPlan>);
    Code:
       0: aload_1
       1: ifnonnull     10
       4: aload_0
       5: iconst_m1
       6: invokevirtual #19                 // Method arc/util/io/Writes.i:(I)V
       9: return
      10: aload_1
      11: invokestatic  #496                // Method getMaxPlans:(Larc/struct/Queue;)I
      14: istore_2
      15: aload_0
      16: iload_2
      17: invokevirtual #19                 // Method arc/util/io/Writes.i:(I)V
      20: iconst_0
      21: istore_3
      22: iload_3
      23: iload_2
      24: if_icmpge     45
      27: aload_0
      28: aload_1
      29: iload_3
      30: invokevirtual #484                // Method arc/struct/Queue.get:(I)Ljava/lang/Object;
      33: checkcast     #487                // class mindustry/entities/units/BuildPlan
      36: invokestatic  #500                // Method writePlan:(Larc/util/io/Writes;Lmindustry/entities/units/BuildPlan;)V
      39: iinc          3, 1
      42: goto          22
      45: return

  public static arc.struct.Queue<mindustry.entities.units.BuildPlan> readPlansQueue(arc.util.io.Reads);
    Code:
       0: aload_0
       1: invokevirtual #211                // Method arc/util/io/Reads.i:()I
       4: istore_1
       5: iload_1
       6: iconst_m1
       7: if_icmpne     12
      10: aconst_null
      11: areturn
      12: new           #477                // class arc/struct/Queue
      15: dup
      16: invokespecial #504                // Method arc/struct/Queue."<init>":()V
      19: astore_2
      20: iconst_0
      21: istore_3
      22: iload_3
      23: iload_1
      24: if_icmpge     41
      27: aload_2
      28: aload_0
      29: invokestatic  #505                // Method readPlan:(Larc/util/io/Reads;)Lmindustry/entities/units/BuildPlan;
      32: invokevirtual #509                // Method arc/struct/Queue.add:(Ljava/lang/Object;)V
      35: iinc          3, 1
      38: goto          22
      41: aload_2
      42: areturn

  public static void writePlan(arc.util.io.Writes, mindustry.entities.units.BuildPlan);
    Code:
       0: aload_0
       1: aload_1
       2: getfield      #512                // Field mindustry/entities/units/BuildPlan.breaking:Z
       5: ifeq          12
       8: iconst_1
       9: goto          13
      12: iconst_0
      13: invokevirtual #7                  // Method arc/util/io/Writes.b:(I)V
      16: aload_0
      17: aload_1
      18: getfield      #515                // Field mindustry/entities/units/BuildPlan.x:I
      21: aload_1
      22: getfield      #516                // Field mindustry/entities/units/BuildPlan.y:I
      25: invokestatic  #460                // Method arc/math/geom/Point2.pack:(II)I
      28: invokevirtual #19                 // Method arc/util/io/Writes.i:(I)V
      31: aload_1
      32: getfield      #512                // Field mindustry/entities/units/BuildPlan.breaking:Z
      35: ifne          71
      38: aload_0
      39: aload_1
      40: getfield      #517                // Field mindustry/entities/units/BuildPlan.block:Lmindustry/world/Block;
      43: getfield      #469                // Field mindustry/world/Block.id:S
      46: invokevirtual #65                 // Method arc/util/io/Writes.s:(I)V
      49: aload_0
      50: aload_1
      51: getfield      #520                // Field mindustry/entities/units/BuildPlan.rotation:I
      54: i2b
      55: invokevirtual #7                  // Method arc/util/io/Writes.b:(I)V
      58: aload_0
      59: iconst_1
      60: invokevirtual #7                  // Method arc/util/io/Writes.b:(I)V
      63: aload_0
      64: aload_1
      65: getfield      #489                // Field mindustry/entities/units/BuildPlan.config:Ljava/lang/Object;
      68: invokestatic  #166                // Method writeObject:(Larc/util/io/Writes;Ljava/lang/Object;)V
      71: return

  public static mindustry.entities.units.BuildPlan readPlan(arc.util.io.Reads);
    Code:
       0: aload_0
       1: invokevirtual #206                // Method arc/util/io/Reads.b:()B
       4: istore_2
       5: aload_0
       6: invokevirtual #211                // Method arc/util/io/Reads.i:()I
       9: istore_3
      10: getstatic     #280                // Field mindustry/Vars.world:Lmindustry/core/World;
      13: iload_3
      14: invokevirtual #466                // Method mindustry/core/World.tile:(I)Lmindustry/world/Tile;
      17: ifnonnull     22
      20: aconst_null
      21: areturn
      22: iload_2
      23: iconst_1
      24: if_icmpne     46
      27: new           #487                // class mindustry/entities/units/BuildPlan
      30: dup
      31: iload_3
      32: invokestatic  #523                // Method arc/math/geom/Point2.x:(I)S
      35: iload_3
      36: invokestatic  #526                // Method arc/math/geom/Point2.y:(I)S
      39: invokespecial #528                // Method mindustry/entities/units/BuildPlan."<init>":(II)V
      42: astore_1
      43: goto          116
      46: aload_0
      47: invokevirtual #240                // Method arc/util/io/Reads.s:()S
      50: istore        4
      52: aload_0
      53: invokevirtual #206                // Method arc/util/io/Reads.b:()B
      56: istore        5
      58: aload_0
      59: invokevirtual #206                // Method arc/util/io/Reads.b:()B
      62: iconst_1
      63: if_icmpne     70
      66: iconst_1
      67: goto          71
      70: iconst_0
      71: istore        6
      73: aload_0
      74: invokestatic  #529                // Method readObject:(Larc/util/io/Reads;)Ljava/lang/Object;
      77: astore        7
      79: new           #487                // class mindustry/entities/units/BuildPlan
      82: dup
      83: iload_3
      84: invokestatic  #523                // Method arc/math/geom/Point2.x:(I)S
      87: iload_3
      88: invokestatic  #526                // Method arc/math/geom/Point2.y:(I)S
      91: iload         5
      93: getstatic     #231                // Field mindustry/Vars.content:Lmindustry/core/ContentLoader;
      96: iload         4
      98: invokevirtual #472                // Method mindustry/core/ContentLoader.block:(I)Lmindustry/world/Block;
     101: invokespecial #532                // Method mindustry/entities/units/BuildPlan."<init>":(IIILmindustry/world/Block;)V
     104: astore_1
     105: iload         6
     107: ifeq          116
     110: aload_1
     111: aload         7
     113: putfield      #489                // Field mindustry/entities/units/BuildPlan.config:Ljava/lang/Object;
     116: aload_1
     117: areturn

  public static void writePlans(arc.util.io.Writes, mindustry.entities.units.BuildPlan[]);
    Code:
       0: aload_1
       1: ifnonnull     10
       4: aload_0
       5: iconst_m1
       6: invokevirtual #65                 // Method arc/util/io/Writes.s:(I)V
       9: return
      10: aload_0
      11: aload_1
      12: arraylength
      13: i2s
      14: invokevirtual #65                 // Method arc/util/io/Writes.s:(I)V
      17: aload_1
      18: astore_2
      19: aload_2
      20: arraylength
      21: istore_3
      22: iconst_0
      23: istore        4
      25: iload         4
      27: iload_3
      28: if_icmpge     49
      31: aload_2
      32: iload         4
      34: aaload
      35: astore        5
      37: aload_0
      38: aload         5
      40: invokestatic  #500                // Method writePlan:(Larc/util/io/Writes;Lmindustry/entities/units/BuildPlan;)V
      43: iinc          4, 1
      46: goto          25
      49: return

  public static mindustry.entities.units.BuildPlan[] readPlans(arc.util.io.Reads);
    Code:
       0: aload_0
       1: invokevirtual #240                // Method arc/util/io/Reads.s:()S
       4: istore_1
       5: iload_1
       6: iconst_m1
       7: if_icmpne     12
      10: aconst_null
      11: areturn
      12: iload_1
      13: anewarray     #487                // class mindustry/entities/units/BuildPlan
      16: astore_2
      17: iconst_0
      18: istore_3
      19: iload_3
      20: iload_1
      21: if_icmpge     46
      24: aload_0
      25: invokestatic  #505                // Method readPlan:(Larc/util/io/Reads;)Lmindustry/entities/units/BuildPlan;
      28: astore        4
      30: aload         4
      32: ifnull        40
      35: aload_2
      36: iload_3
      37: aload         4
      39: aastore
      40: iinc          3, 1
      43: goto          19
      46: aload_2
      47: areturn

  public static void writeController(arc.util.io.Writes, mindustry.entities.units.UnitController);
    Code:
       0: aload_1
       1: instanceof    #535                // class mindustry/gen/Player
       4: ifeq          28
       7: aload_1
       8: checkcast     #535                // class mindustry/gen/Player
      11: astore_2
      12: aload_0
      13: iconst_0
      14: invokevirtual #7                  // Method arc/util/io/Writes.b:(I)V
      17: aload_0
      18: aload_2
      19: getfield      #537                // Field mindustry/gen/Player.id:I
      22: invokevirtual #19                 // Method arc/util/io/Writes.i:(I)V
      25: goto          513
      28: aload_1
      29: instanceof    #538                // class mindustry/ai/types/LogicAI
      32: ifeq          66
      35: aload_1
      36: checkcast     #538                // class mindustry/ai/types/LogicAI
      39: astore_3
      40: aload_3
      41: getfield      #540                // Field mindustry/ai/types/LogicAI.controller:Lmindustry/gen/Building;
      44: ifnull        66
      47: aload_0
      48: iconst_3
      49: invokevirtual #7                  // Method arc/util/io/Writes.b:(I)V
      52: aload_0
      53: aload_3
      54: getfield      #540                // Field mindustry/ai/types/LogicAI.controller:Lmindustry/gen/Building;
      57: invokevirtual #123                // Method mindustry/gen/Building.pos:()I
      60: invokevirtual #19                 // Method arc/util/io/Writes.i:(I)V
      63: goto          513
      66: aload_1
      67: instanceof    #544                // class mindustry/ai/types/CommandAI
      70: ifeq          493
      73: aload_1
      74: checkcast     #544                // class mindustry/ai/types/CommandAI
      77: astore        4
      79: aload_0
      80: bipush        9
      82: invokevirtual #7                  // Method arc/util/io/Writes.b:(I)V
      85: aload_0
      86: aload         4
      88: getfield      #546                // Field mindustry/ai/types/CommandAI.attackTarget:Lmindustry/gen/Teamc;
      91: ifnull        98
      94: iconst_1
      95: goto          99
      98: iconst_0
      99: invokevirtual #107                // Method arc/util/io/Writes.bool:(Z)V
     102: aload_0
     103: aload         4
     105: getfield      #550                // Field mindustry/ai/types/CommandAI.targetPos:Larc/math/geom/Vec2;
     108: ifnull        115
     111: iconst_1
     112: goto          116
     115: iconst_0
     116: invokevirtual #107                // Method arc/util/io/Writes.bool:(Z)V
     119: aload         4
     121: getfield      #550                // Field mindustry/ai/types/CommandAI.targetPos:Larc/math/geom/Vec2;
     124: ifnull        151
     127: aload_0
     128: aload         4
     130: getfield      #550                // Field mindustry/ai/types/CommandAI.targetPos:Larc/math/geom/Vec2;
     133: getfield      #149                // Field arc/math/geom/Vec2.x:F
     136: invokevirtual #38                 // Method arc/util/io/Writes.f:(F)V
     139: aload_0
     140: aload         4
     142: getfield      #550                // Field mindustry/ai/types/CommandAI.targetPos:Larc/math/geom/Vec2;
     145: getfield      #154                // Field arc/math/geom/Vec2.y:F
     148: invokevirtual #38                 // Method arc/util/io/Writes.f:(F)V
     151: aload         4
     153: getfield      #546                // Field mindustry/ai/types/CommandAI.attackTarget:Lmindustry/gen/Teamc;
     156: ifnull        228
     159: aload_0
     160: aload         4
     162: getfield      #546                // Field mindustry/ai/types/CommandAI.attackTarget:Lmindustry/gen/Teamc;
     165: instanceof    #121                // class mindustry/gen/Building
     168: ifeq          175
     171: iconst_1
     172: goto          176
     175: iconst_0
     176: invokevirtual #7                  // Method arc/util/io/Writes.b:(I)V
     179: aload         4
     181: getfield      #546                // Field mindustry/ai/types/CommandAI.attackTarget:Lmindustry/gen/Teamc;
     184: astore        6
     186: aload         6
     188: instanceof    #121                // class mindustry/gen/Building
     191: ifeq          213
     194: aload         6
     196: checkcast     #121                // class mindustry/gen/Building
     199: astore        5
     201: aload_0
     202: aload         5
     204: invokevirtual #123                // Method mindustry/gen/Building.pos:()I
     207: invokevirtual #19                 // Method arc/util/io/Writes.i:(I)V
     210: goto          228
     213: aload_0
     214: aload         4
     216: getfield      #546                // Field mindustry/ai/types/CommandAI.attackTarget:Lmindustry/gen/Teamc;
     219: checkcast     #140                // class mindustry/gen/Unit
     222: getfield      #142                // Field mindustry/gen/Unit.id:I
     225: invokevirtual #19                 // Method arc/util/io/Writes.i:(I)V
     228: aload_0
     229: aload         4
     231: getfield      #554                // Field mindustry/ai/types/CommandAI.command:Lmindustry/ai/UnitCommand;
     234: ifnonnull     241
     237: iconst_m1
     238: goto          249
     241: aload         4
     243: getfield      #554                // Field mindustry/ai/types/CommandAI.command:Lmindustry/ai/UnitCommand;
     246: getfield      #172                // Field mindustry/ai/UnitCommand.id:S
     249: invokevirtual #7                  // Method arc/util/io/Writes.b:(I)V
     252: aload_0
     253: aload         4
     255: getfield      #558                // Field mindustry/ai/types/CommandAI.commandQueue:Larc/struct/Seq;
     258: getfield      #443                // Field arc/struct/Seq.size:I
     261: invokevirtual #7                  // Method arc/util/io/Writes.b:(I)V
     264: aload         4
     266: getfield      #558                // Field mindustry/ai/types/CommandAI.commandQueue:Larc/struct/Seq;
     269: invokevirtual #562                // Method arc/struct/Seq.iterator:()Ljava/util/Iterator;
     272: astore        5
     274: aload         5
     276: invokeinterface #566,  1          // InterfaceMethod java/util/Iterator.hasNext:()Z
     281: ifeq          409
     284: aload         5
     286: invokeinterface #571,  1          // InterfaceMethod java/util/Iterator.next:()Ljava/lang/Object;
     291: checkcast     #574                // class arc/math/geom/Position
     294: astore        6
     296: aload         6
     298: instanceof    #121                // class mindustry/gen/Building
     301: ifeq          328
     304: aload         6
     306: checkcast     #121                // class mindustry/gen/Building
     309: astore        7
     311: aload_0
     312: iconst_0
     313: invokevirtual #7                  // Method arc/util/io/Writes.b:(I)V
     316: aload_0
     317: aload         7
     319: invokevirtual #123                // Method mindustry/gen/Building.pos:()I
     322: invokevirtual #19                 // Method arc/util/io/Writes.i:(I)V
     325: goto          406
     328: aload         6
     330: instanceof    #140                // class mindustry/gen/Unit
     333: ifeq          360
     336: aload         6
     338: checkcast     #140                // class mindustry/gen/Unit
     341: astore        8
     343: aload_0
     344: iconst_1
     345: invokevirtual #7                  // Method arc/util/io/Writes.b:(I)V
     348: aload_0
     349: aload         8
     351: getfield      #142                // Field mindustry/gen/Unit.id:I
     354: invokevirtual #19                 // Method arc/util/io/Writes.i:(I)V
     357: goto          406
     360: aload         6
     362: instanceof    #150                // class arc/math/geom/Vec2
     365: ifeq          401
     368: aload         6
     370: checkcast     #150                // class arc/math/geom/Vec2
     373: astore        9
     375: aload_0
     376: iconst_2
     377: invokevirtual #7                  // Method arc/util/io/Writes.b:(I)V
     380: aload_0
     381: aload         9
     383: getfield      #149                // Field arc/math/geom/Vec2.x:F
     386: invokevirtual #38                 // Method arc/util/io/Writes.f:(F)V
     389: aload_0
     390: aload         9
     392: getfield      #154                // Field arc/math/geom/Vec2.y:F
     395: invokevirtual #38                 // Method arc/util/io/Writes.f:(F)V
     398: goto          406
     401: aload_0
     402: iconst_3
     403: invokevirtual #7                  // Method arc/util/io/Writes.b:(I)V
     406: goto          274
     409: getstatic     #231                // Field mindustry/Vars.content:Lmindustry/core/ContentLoader;
     412: invokevirtual #439                // Method mindustry/core/ContentLoader.unitStances:()Larc/struct/Seq;
     415: aload         4
     417: dup
     418: invokestatic  #576                // Method java/util/Objects.requireNonNull:(Ljava/lang/Object;)Ljava/lang/Object;
     421: pop
     422: invokedynamic #582,  0            // InvokeDynamic #0:get:(Lmindustry/ai/types/CommandAI;)Larc/func/Boolf;
     427: invokevirtual #585                // Method arc/struct/Seq.count:(Larc/func/Boolf;)I
     430: istore        5
     432: aload_0
     433: iload         5
     435: invokevirtual #7                  // Method arc/util/io/Writes.b:(I)V
     438: getstatic     #231                // Field mindustry/Vars.content:Lmindustry/core/ContentLoader;
     441: invokevirtual #439                // Method mindustry/core/ContentLoader.unitStances:()Larc/struct/Seq;
     444: invokevirtual #562                // Method arc/struct/Seq.iterator:()Ljava/util/Iterator;
     447: astore        6
     449: aload         6
     451: invokeinterface #566,  1          // InterfaceMethod java/util/Iterator.hasNext:()Z
     456: ifeq          490
     459: aload         6
     461: invokeinterface #571,  1          // InterfaceMethod java/util/Iterator.next:()Ljava/lang/Object;
     466: checkcast     #437                // class mindustry/ai/UnitStance
     469: astore        7
     471: aload         4
     473: aload         7
     475: invokevirtual #589                // Method mindustry/ai/types/CommandAI.hasStance:(Lmindustry/ai/UnitStance;)Z
     478: ifeq          487
     481: aload_0
     482: aload         7
     484: invokestatic  #593                // Method writeStance:(Larc/util/io/Writes;Lmindustry/ai/UnitStance;)V
     487: goto          449
     490: goto          513
     493: aload_1
     494: instanceof    #597                // class mindustry/ai/types/AssemblerAI
     497: ifeq          508
     500: aload_0
     501: iconst_5
     502: invokevirtual #7                  // Method arc/util/io/Writes.b:(I)V
     505: goto          513
     508: aload_0
     509: iconst_2
     510: invokevirtual #7                  // Method arc/util/io/Writes.b:(I)V
     513: return

  public static mindustry.entities.units.UnitController readController(arc.util.io.Reads, mindustry.entities.units.UnitController);
    Code:
       0: aload_0
       1: invokevirtual #206                // Method arc/util/io/Reads.b:()B
       4: istore_2
       5: iload_2
       6: ifne          36
       9: aload_0
      10: invokevirtual #211                // Method arc/util/io/Reads.i:()I
      13: istore_3
      14: getstatic     #599                // Field mindustry/gen/Groups.player:Lmindustry/entities/EntityGroup;
      17: iload_3
      18: invokevirtual #303                // Method mindustry/entities/EntityGroup.getByID:(I)Lmindustry/gen/Entityc;
      21: checkcast     #535                // class mindustry/gen/Player
      24: astore        4
      26: aload         4
      28: ifnonnull     33
      31: aload_1
      32: areturn
      33: aload         4
      35: areturn
      36: iload_2
      37: iconst_1
      38: if_icmpne     48
      41: aload_0
      42: invokevirtual #211                // Method arc/util/io/Reads.i:()I
      45: pop
      46: aload_1
      47: areturn
      48: iload_2
      49: iconst_3
      50: if_icmpne     118
      53: aload_0
      54: invokevirtual #211                // Method arc/util/io/Reads.i:()I
      57: istore_3
      58: aload_1
      59: instanceof    #538                // class mindustry/ai/types/LogicAI
      62: ifeq          86
      65: aload_1
      66: checkcast     #538                // class mindustry/ai/types/LogicAI
      69: astore        4
      71: aload         4
      73: getstatic     #280                // Field mindustry/Vars.world:Lmindustry/core/World;
      76: iload_3
      77: invokevirtual #284                // Method mindustry/core/World.build:(I)Lmindustry/gen/Building;
      80: putfield      #540                // Field mindustry/ai/types/LogicAI.controller:Lmindustry/gen/Building;
      83: aload         4
      85: areturn
      86: new           #538                // class mindustry/ai/types/LogicAI
      89: dup
      90: invokespecial #602                // Method mindustry/ai/types/LogicAI."<init>":()V
      93: astore        5
      95: aload         5
      97: ldc_w         #603                // float 600.0f
     100: putfield      #604                // Field mindustry/ai/types/LogicAI.controlTimer:F
     103: aload         5
     105: getstatic     #280                // Field mindustry/Vars.world:Lmindustry/core/World;
     108: iload_3
     109: invokevirtual #284                // Method mindustry/core/World.build:(I)Lmindustry/gen/Building;
     112: putfield      #540                // Field mindustry/ai/types/LogicAI.controller:Lmindustry/gen/Building;
     115: aload         5
     117: areturn
     118: iload_2
     119: iconst_4
     120: if_icmpeq     147
     123: iload_2
     124: bipush        6
     126: if_icmpeq     147
     129: iload_2
     130: bipush        7
     132: if_icmpeq     147
     135: iload_2
     136: bipush        8
     138: if_icmpeq     147
     141: iload_2
     142: bipush        9
     144: if_icmpne     595
     147: aload_1
     148: instanceof    #544                // class mindustry/ai/types/CommandAI
     151: ifeq          165
     154: aload_1
     155: checkcast     #544                // class mindustry/ai/types/CommandAI
     158: astore        4
     160: aload         4
     162: goto          172
     165: new           #544                // class mindustry/ai/types/CommandAI
     168: dup
     169: invokespecial #607                // Method mindustry/ai/types/CommandAI."<init>":()V
     172: astore_3
     173: aload_0
     174: invokevirtual #270                // Method arc/util/io/Reads.bool:()Z
     177: istore        4
     179: aload_0
     180: invokevirtual #270                // Method arc/util/io/Reads.bool:()Z
     183: istore        5
     185: iload         5
     187: ifeq          227
     190: aload_3
     191: getfield      #550                // Field mindustry/ai/types/CommandAI.targetPos:Larc/math/geom/Vec2;
     194: ifnonnull     208
     197: aload_3
     198: new           #150                // class arc/math/geom/Vec2
     201: dup
     202: invokespecial #608                // Method arc/math/geom/Vec2."<init>":()V
     205: putfield      #550                // Field mindustry/ai/types/CommandAI.targetPos:Larc/math/geom/Vec2;
     208: aload_3
     209: getfield      #550                // Field mindustry/ai/types/CommandAI.targetPos:Larc/math/geom/Vec2;
     212: aload_0
     213: invokevirtual #222                // Method arc/util/io/Reads.f:()F
     216: aload_0
     217: invokevirtual #222                // Method arc/util/io/Reads.f:()F
     220: invokevirtual #609                // Method arc/math/geom/Vec2.set:(FF)Larc/math/geom/Vec2;
     223: pop
     224: goto          232
     227: aload_3
     228: aconst_null
     229: putfield      #550                // Field mindustry/ai/types/CommandAI.targetPos:Larc/math/geom/Vec2;
     232: aload_3
     233: invokevirtual #613                // Method mindustry/ai/types/CommandAI.setupLastPos:()V
     236: aload_3
     237: iconst_m1
     238: putfield      #616                // Field mindustry/ai/types/CommandAI.readAttackTarget:I
     241: iload         4
     243: ifeq          300
     246: aload_0
     247: invokevirtual #206                // Method arc/util/io/Reads.b:()B
     250: istore        6
     252: iload         6
     254: iconst_1
     255: if_icmpne     275
     258: aload_3
     259: getstatic     #280                // Field mindustry/Vars.world:Lmindustry/core/World;
     262: aload_0
     263: invokevirtual #211                // Method arc/util/io/Reads.i:()I
     266: invokevirtual #284                // Method mindustry/core/World.build:(I)Lmindustry/gen/Building;
     269: putfield      #546                // Field mindustry/ai/types/CommandAI.attackTarget:Lmindustry/gen/Teamc;
     272: goto          297
     275: aload_3
     276: getstatic     #297                // Field mindustry/gen/Groups.unit:Lmindustry/entities/EntityGroup;
     279: aload_3
     280: aload_0
     281: invokevirtual #211                // Method arc/util/io/Reads.i:()I
     284: dup_x1
     285: putfield      #616                // Field mindustry/ai/types/CommandAI.readAttackTarget:I
     288: invokevirtual #303                // Method mindustry/entities/EntityGroup.getByID:(I)Lmindustry/gen/Entityc;
     291: checkcast     #619                // class mindustry/gen/Teamc
     294: putfield      #546                // Field mindustry/ai/types/CommandAI.attackTarget:Lmindustry/gen/Teamc;
     297: goto          305
     300: aload_3
     301: aconst_null
     302: putfield      #546                // Field mindustry/ai/types/CommandAI.attackTarget:Lmindustry/gen/Teamc;
     305: iload_2
     306: bipush        6
     308: if_icmpeq     329
     311: iload_2
     312: bipush        7
     314: if_icmpeq     329
     317: iload_2
     318: bipush        8
     320: if_icmpeq     329
     323: iload_2
     324: bipush        9
     326: if_icmpne     370
     329: aload_0
     330: invokevirtual #206                // Method arc/util/io/Reads.b:()B
     333: istore        6
     335: aload_3
     336: iload         6
     338: ifge          345
     341: aconst_null
     342: goto          353
     345: getstatic     #231                // Field mindustry/Vars.content:Lmindustry/core/ContentLoader;
     348: iload         6
     350: invokevirtual #325                // Method mindustry/core/ContentLoader.unitCommand:(I)Lmindustry/ai/UnitCommand;
     353: putfield      #554                // Field mindustry/ai/types/CommandAI.command:Lmindustry/ai/UnitCommand;
     356: aload_3
     357: getfield      #554                // Field mindustry/ai/types/CommandAI.command:Lmindustry/ai/UnitCommand;
     360: ifnonnull     370
     363: aload_3
     364: getstatic     #621                // Field mindustry/ai/UnitCommand.moveCommand:Lmindustry/ai/UnitCommand;
     367: putfield      #554                // Field mindustry/ai/types/CommandAI.command:Lmindustry/ai/UnitCommand;
     370: iload_2
     371: bipush        7
     373: if_icmpeq     388
     376: iload_2
     377: bipush        8
     379: if_icmpeq     388
     382: iload_2
     383: bipush        9
     385: if_icmpne     540
     388: aload_3
     389: getfield      #558                // Field mindustry/ai/types/CommandAI.commandQueue:Larc/struct/Seq;
     392: invokevirtual #624                // Method arc/struct/Seq.clear:()Larc/struct/Seq;
     395: pop
     396: aload_0
     397: invokevirtual #315                // Method arc/util/io/Reads.ub:()I
     400: istore        6
     402: iconst_0
     403: istore        7
     405: iload         7
     407: iload         6
     409: if_icmpge     540
     412: aload_0
     413: invokevirtual #206                // Method arc/util/io/Reads.b:()B
     416: istore        8
     418: iload         8
     420: tableswitch   { // 0 to 2
                     0: 448
                     1: 478
                     2: 511
               default: 534
          }
     448: getstatic     #280                // Field mindustry/Vars.world:Lmindustry/core/World;
     451: aload_0
     452: invokevirtual #211                // Method arc/util/io/Reads.i:()I
     455: invokevirtual #284                // Method mindustry/core/World.build:(I)Lmindustry/gen/Building;
     458: astore        9
     460: aload         9
     462: ifnull        475
     465: aload_3
     466: getfield      #558                // Field mindustry/ai/types/CommandAI.commandQueue:Larc/struct/Seq;
     469: aload         9
     471: invokevirtual #627                // Method arc/struct/Seq.add:(Ljava/lang/Object;)Larc/struct/Seq;
     474: pop
     475: goto          534
     478: getstatic     #297                // Field mindustry/gen/Groups.unit:Lmindustry/entities/EntityGroup;
     481: aload_0
     482: invokevirtual #211                // Method arc/util/io/Reads.i:()I
     485: invokevirtual #303                // Method mindustry/entities/EntityGroup.getByID:(I)Lmindustry/gen/Entityc;
     488: checkcast     #140                // class mindustry/gen/Unit
     491: astore        9
     493: aload         9
     495: ifnull        508
     498: aload_3
     499: getfield      #558                // Field mindustry/ai/types/CommandAI.commandQueue:Larc/struct/Seq;
     502: aload         9
     504: invokevirtual #627                // Method arc/struct/Seq.add:(Ljava/lang/Object;)Larc/struct/Seq;
     507: pop
     508: goto          534
     511: aload_3
     512: getfield      #558                // Field mindustry/ai/types/CommandAI.commandQueue:Larc/struct/Seq;
     515: new           #150                // class arc/math/geom/Vec2
     518: dup
     519: aload_0
     520: invokevirtual #222                // Method arc/util/io/Reads.f:()F
     523: aload_0
     524: invokevirtual #222                // Method arc/util/io/Reads.f:()F
     527: invokespecial #309                // Method arc/math/geom/Vec2."<init>":(FF)V
     530: invokevirtual #627                // Method arc/struct/Seq.add:(Ljava/lang/Object;)Larc/struct/Seq;
     533: pop
     534: iinc          7, 1
     537: goto          405
     540: iload_2
     541: bipush        8
     543: if_icmpne     557
     546: aload_3
     547: aload_0
     548: invokestatic  #630                // Method readStance:(Larc/util/io/Reads;)Lmindustry/ai/UnitStance;
     551: invokevirtual #634                // Method mindustry/ai/types/CommandAI.setStance:(Lmindustry/ai/UnitStance;)V
     554: goto          593
     557: iload_2
     558: bipush        9
     560: if_icmpne     593
     563: aload_0
     564: invokevirtual #315                // Method arc/util/io/Reads.ub:()I
     567: istore        6
     569: iconst_0
     570: istore        7
     572: iload         7
     574: iload         6
     576: if_icmpge     593
     579: aload_3
     580: aload_0
     581: invokestatic  #630                // Method readStance:(Larc/util/io/Reads;)Lmindustry/ai/UnitStance;
     584: invokevirtual #634                // Method mindustry/ai/types/CommandAI.setStance:(Lmindustry/ai/UnitStance;)V
     587: iinc          7, 1
     590: goto          572
     593: aload_3
     594: areturn
     595: iload_2
     596: iconst_5
     597: if_icmpne     619
     600: aload_1
     601: instanceof    #597                // class mindustry/ai/types/AssemblerAI
     604: ifeq          611
     607: aload_1
     608: goto          618
     611: new           #597                // class mindustry/ai/types/AssemblerAI
     614: dup
     615: invokespecial #638                // Method mindustry/ai/types/AssemblerAI."<init>":()V
     618: areturn
     619: aload_1
     620: instanceof    #639                // class mindustry/entities/units/AIController
     623: ifeq          633
     626: aload_1
     627: instanceof    #538                // class mindustry/ai/types/LogicAI
     630: ifeq          643
     633: new           #641                // class mindustry/ai/types/GroundAI
     636: dup
     637: invokespecial #643                // Method mindustry/ai/types/GroundAI."<init>":()V
     640: goto          644
     643: aload_1
     644: areturn

  public static void writeKick(arc.util.io.Writes, mindustry.net.Packets$KickReason);
    Code:
       0: aload_0
       1: aload_1
       2: invokevirtual #644                // Method mindustry/net/Packets$KickReason.ordinal:()I
       5: i2b
       6: invokevirtual #7                  // Method arc/util/io/Writes.b:(I)V
       9: return

  public static mindustry.net.Packets$KickReason readKick(arc.util.io.Reads);
    Code:
       0: getstatic     #647                // Field mindustry/net/Packets$KickReason.all:[Lmindustry/net/Packets$KickReason;
       3: aload_0
       4: invokevirtual #206                // Method arc/util/io/Reads.b:()B
       7: aaload
       8: areturn

  public static void writeMarkerControl(arc.util.io.Writes, mindustry.logic.LMarkerControl);
    Code:
       0: aload_0
       1: aload_1
       2: invokevirtual #650                // Method mindustry/logic/LMarkerControl.ordinal:()I
       5: i2b
       6: invokevirtual #7                  // Method arc/util/io/Writes.b:(I)V
       9: return

  public static mindustry.logic.LMarkerControl readMarkerControl(arc.util.io.Reads);
    Code:
       0: getstatic     #653                // Field mindustry/logic/LMarkerControl.all:[Lmindustry/logic/LMarkerControl;
       3: aload_0
       4: invokevirtual #315                // Method arc/util/io/Reads.ub:()I
       7: aaload
       8: areturn

  public static void writeRules(arc.util.io.Writes, mindustry.game.Rules);
    Code:
       0: aload_1
       1: invokestatic  #656                // Method mindustry/io/JsonIO.write:(Ljava/lang/Object;)Ljava/lang/String;
       4: astore_2
       5: aload_2
       6: getstatic     #661                // Field mindustry/Vars.charset:Ljava/nio/charset/Charset;
       9: invokevirtual #665                // Method java/lang/String.getBytes:(Ljava/nio/charset/Charset;)[B
      12: astore_3
      13: aload_0
      14: aload_3
      15: arraylength
      16: invokevirtual #19                 // Method arc/util/io/Writes.i:(I)V
      19: aload_0
      20: aload_3
      21: invokevirtual #135                // Method arc/util/io/Writes.b:([B)V
      24: return

  public static mindustry.game.Rules readRules(arc.util.io.Reads);
    Code:
       0: aload_0
       1: invokevirtual #211                // Method arc/util/io/Reads.i:()I
       4: istore_1
       5: new           #42                 // class java/lang/String
       8: dup
       9: aload_0
      10: iload_1
      11: newarray       byte
      13: invokevirtual #294                // Method arc/util/io/Reads.b:([B)[B
      16: getstatic     #661                // Field mindustry/Vars.charset:Ljava/nio/charset/Charset;
      19: invokespecial #669                // Method java/lang/String."<init>":([BLjava/nio/charset/Charset;)V
      22: astore_2
      23: ldc_w         #672                // class mindustry/game/Rules
      26: aload_2
      27: invokestatic  #674                // Method mindustry/io/JsonIO.read:(Ljava/lang/Class;Ljava/lang/String;)Ljava/lang/Object;
      30: checkcast     #672                // class mindustry/game/Rules
      33: areturn

  public static void writeObjectives(arc.util.io.Writes, mindustry.game.MapObjectives);
    Code:
       0: aload_1
       1: invokestatic  #656                // Method mindustry/io/JsonIO.write:(Ljava/lang/Object;)Ljava/lang/String;
       4: astore_2
       5: aload_2
       6: getstatic     #661                // Field mindustry/Vars.charset:Ljava/nio/charset/Charset;
       9: invokevirtual #665                // Method java/lang/String.getBytes:(Ljava/nio/charset/Charset;)[B
      12: astore_3
      13: aload_0
      14: aload_3
      15: arraylength
      16: invokevirtual #19                 // Method arc/util/io/Writes.i:(I)V
      19: aload_0
      20: aload_3
      21: invokevirtual #135                // Method arc/util/io/Writes.b:([B)V
      24: return

  public static mindustry.game.MapObjectives readObjectives(arc.util.io.Reads);
    Code:
       0: aload_0
       1: invokevirtual #211                // Method arc/util/io/Reads.i:()I
       4: istore_1
       5: new           #42                 // class java/lang/String
       8: dup
       9: aload_0
      10: iload_1
      11: newarray       byte
      13: invokevirtual #294                // Method arc/util/io/Reads.b:([B)[B
      16: getstatic     #661                // Field mindustry/Vars.charset:Ljava/nio/charset/Charset;
      19: invokespecial #669                // Method java/lang/String."<init>":([BLjava/nio/charset/Charset;)V
      22: astore_2
      23: ldc_w         #677                // class mindustry/game/MapObjectives
      26: aload_2
      27: invokestatic  #674                // Method mindustry/io/JsonIO.read:(Ljava/lang/Class;Ljava/lang/String;)Ljava/lang/Object;
      30: checkcast     #677                // class mindustry/game/MapObjectives
      33: areturn

  public static void writeObjectiveMarker(arc.util.io.Writes, mindustry.game.MapObjectives$ObjectiveMarker);
    Code:
       0: getstatic     #679                // Field mindustry/io/JsonIO.json:Larc/util/serialization/Json;
       3: aload_1
       4: ldc_w         #683                // class mindustry/game/MapObjectives$ObjectiveMarker
       7: invokevirtual #685                // Method arc/util/serialization/Json.toJson:(Ljava/lang/Object;Ljava/lang/Class;)Ljava/lang/String;
      10: astore_2
      11: aload_2
      12: getstatic     #661                // Field mindustry/Vars.charset:Ljava/nio/charset/Charset;
      15: invokevirtual #665                // Method java/lang/String.getBytes:(Ljava/nio/charset/Charset;)[B
      18: astore_3
      19: aload_0
      20: aload_3
      21: arraylength
      22: invokevirtual #19                 // Method arc/util/io/Writes.i:(I)V
      25: aload_0
      26: aload_3
      27: invokevirtual #135                // Method arc/util/io/Writes.b:([B)V
      30: return

  public static mindustry.game.MapObjectives$ObjectiveMarker readObjectiveMarker(arc.util.io.Reads);
    Code:
       0: aload_0
       1: invokevirtual #211                // Method arc/util/io/Reads.i:()I
       4: istore_1
       5: new           #42                 // class java/lang/String
       8: dup
       9: aload_0
      10: iload_1
      11: newarray       byte
      13: invokevirtual #294                // Method arc/util/io/Reads.b:([B)[B
      16: getstatic     #661                // Field mindustry/Vars.charset:Ljava/nio/charset/Charset;
      19: invokespecial #669                // Method java/lang/String."<init>":([BLjava/nio/charset/Charset;)V
      22: astore_2
      23: ldc_w         #683                // class mindustry/game/MapObjectives$ObjectiveMarker
      26: aload_2
      27: invokestatic  #674                // Method mindustry/io/JsonIO.read:(Ljava/lang/Class;Ljava/lang/String;)Ljava/lang/Object;
      30: checkcast     #683                // class mindustry/game/MapObjectives$ObjectiveMarker
      33: areturn

  public static void writeVecNullable(arc.util.io.Writes, arc.math.geom.Vec2);
    Code:
       0: aload_1
       1: ifnonnull     21
       4: aload_0
       5: ldc_w         #691                // float NaNf
       8: invokevirtual #38                 // Method arc/util/io/Writes.f:(F)V
      11: aload_0
      12: ldc_w         #691                // float NaNf
      15: invokevirtual #38                 // Method arc/util/io/Writes.f:(F)V
      18: goto          37
      21: aload_0
      22: aload_1
      23: getfield      #149                // Field arc/math/geom/Vec2.x:F
      26: invokevirtual #38                 // Method arc/util/io/Writes.f:(F)V
      29: aload_0
      30: aload_1
      31: getfield      #154                // Field arc/math/geom/Vec2.y:F
      34: invokevirtual #38                 // Method arc/util/io/Writes.f:(F)V
      37: return

  public static arc.math.geom.Vec2 readVecNullable(arc.util.io.Reads);
    Code:
       0: aload_0
       1: invokevirtual #222                // Method arc/util/io/Reads.f:()F
       4: fstore_1
       5: aload_0
       6: invokevirtual #222                // Method arc/util/io/Reads.f:()F
       9: fstore_2
      10: fload_1
      11: invokestatic  #692                // Method java/lang/Float.isNaN:(F)Z
      14: ifne          24
      17: fload_2
      18: invokestatic  #692                // Method java/lang/Float.isNaN:(F)Z
      21: ifeq          28
      24: aconst_null
      25: goto          37
      28: new           #150                // class arc/math/geom/Vec2
      31: dup
      32: fload_1
      33: fload_2
      34: invokespecial #309                // Method arc/math/geom/Vec2."<init>":(FF)V
      37: areturn

  public static void writeVec2(arc.util.io.Writes, arc.math.geom.Vec2);
    Code:
       0: aload_1
       1: ifnonnull     17
       4: aload_0
       5: fconst_0
       6: invokevirtual #38                 // Method arc/util/io/Writes.f:(F)V
       9: aload_0
      10: fconst_0
      11: invokevirtual #38                 // Method arc/util/io/Writes.f:(F)V
      14: goto          33
      17: aload_0
      18: aload_1
      19: getfield      #149                // Field arc/math/geom/Vec2.x:F
      22: invokevirtual #38                 // Method arc/util/io/Writes.f:(F)V
      25: aload_0
      26: aload_1
      27: getfield      #154                // Field arc/math/geom/Vec2.y:F
      30: invokevirtual #38                 // Method arc/util/io/Writes.f:(F)V
      33: return

  public static arc.math.geom.Vec2 readVec2(arc.util.io.Reads, arc.math.geom.Vec2);
    Code:
       0: aload_1
       1: aload_0
       2: invokevirtual #222                // Method arc/util/io/Reads.f:()F
       5: aload_0
       6: invokevirtual #222                // Method arc/util/io/Reads.f:()F
       9: invokevirtual #609                // Method arc/math/geom/Vec2.set:(FF)Larc/math/geom/Vec2;
      12: areturn

  public static arc.math.geom.Vec2 readVec2(arc.util.io.Reads);
    Code:
       0: new           #150                // class arc/math/geom/Vec2
       3: dup
       4: aload_0
       5: invokevirtual #222                // Method arc/util/io/Reads.f:()F
       8: aload_0
       9: invokevirtual #222                // Method arc/util/io/Reads.f:()F
      12: invokespecial #309                // Method arc/math/geom/Vec2."<init>":(FF)V
      15: areturn

  public static void writeStatus(arc.util.io.Writes, mindustry.entities.units.StatusEntry);
    Code:
       0: aload_0
       1: aload_1
       2: getfield      #696                // Field mindustry/entities/units/StatusEntry.effect:Lmindustry/type/StatusEffect;
       5: getfield      #702                // Field mindustry/type/StatusEffect.id:S
       8: invokevirtual #65                 // Method arc/util/io/Writes.s:(I)V
      11: aload_0
      12: aload_1
      13: getfield      #705                // Field mindustry/entities/units/StatusEntry.time:F
      16: invokevirtual #38                 // Method arc/util/io/Writes.f:(F)V
      19: aload_1
      20: getfield      #696                // Field mindustry/entities/units/StatusEntry.effect:Lmindustry/type/StatusEffect;
      23: getfield      #708                // Field mindustry/type/StatusEffect.dynamic:Z
      26: ifeq          260
      29: aload_0
      30: aload_1
      31: getfield      #711                // Field mindustry/entities/units/StatusEntry.damageMultiplier:F
      34: fconst_1
      35: fcmpl
      36: ifeq          43
      39: iconst_1
      40: goto          44
      43: iconst_0
      44: aload_1
      45: getfield      #714                // Field mindustry/entities/units/StatusEntry.healthMultiplier:F
      48: fconst_1
      49: fcmpl
      50: ifeq          57
      53: iconst_2
      54: goto          58
      57: iconst_0
      58: ior
      59: aload_1
      60: getfield      #717                // Field mindustry/entities/units/StatusEntry.speedMultiplier:F
      63: fconst_1
      64: fcmpl
      65: ifeq          72
      68: iconst_4
      69: goto          73
      72: iconst_0
      73: ior
      74: aload_1
      75: getfield      #720                // Field mindustry/entities/units/StatusEntry.reloadMultiplier:F
      78: fconst_1
      79: fcmpl
      80: ifeq          88
      83: bipush        8
      85: goto          89
      88: iconst_0
      89: ior
      90: aload_1
      91: getfield      #723                // Field mindustry/entities/units/StatusEntry.buildSpeedMultiplier:F
      94: fconst_1
      95: fcmpl
      96: ifeq          104
      99: bipush        16
     101: goto          105
     104: iconst_0
     105: ior
     106: aload_1
     107: getfield      #726                // Field mindustry/entities/units/StatusEntry.dragMultiplier:F
     110: fconst_1
     111: fcmpl
     112: ifeq          120
     115: bipush        32
     117: goto          121
     120: iconst_0
     121: ior
     122: aload_1
     123: getfield      #729                // Field mindustry/entities/units/StatusEntry.armorOverride:F
     126: fconst_0
     127: fcmpl
     128: iflt          136
     131: bipush        64
     133: goto          137
     136: iconst_0
     137: ior
     138: invokevirtual #7                  // Method arc/util/io/Writes.b:(I)V
     141: aload_1
     142: getfield      #711                // Field mindustry/entities/units/StatusEntry.damageMultiplier:F
     145: fconst_1
     146: fcmpl
     147: ifeq          158
     150: aload_0
     151: aload_1
     152: getfield      #711                // Field mindustry/entities/units/StatusEntry.damageMultiplier:F
     155: invokevirtual #38                 // Method arc/util/io/Writes.f:(F)V
     158: aload_1
     159: getfield      #714                // Field mindustry/entities/units/StatusEntry.healthMultiplier:F
     162: fconst_1
     163: fcmpl
     164: ifeq          175
     167: aload_0
     168: aload_1
     169: getfield      #714                // Field mindustry/entities/units/StatusEntry.healthMultiplier:F
     172: invokevirtual #38                 // Method arc/util/io/Writes.f:(F)V
     175: aload_1
     176: getfield      #717                // Field mindustry/entities/units/StatusEntry.speedMultiplier:F
     179: fconst_1
     180: fcmpl
     181: ifeq          192
     184: aload_0
     185: aload_1
     186: getfield      #717                // Field mindustry/entities/units/StatusEntry.speedMultiplier:F
     189: invokevirtual #38                 // Method arc/util/io/Writes.f:(F)V
     192: aload_1
     193: getfield      #720                // Field mindustry/entities/units/StatusEntry.reloadMultiplier:F
     196: fconst_1
     197: fcmpl
     198: ifeq          209
     201: aload_0
     202: aload_1
     203: getfield      #720                // Field mindustry/entities/units/StatusEntry.reloadMultiplier:F
     206: invokevirtual #38                 // Method arc/util/io/Writes.f:(F)V
     209: aload_1
     210: getfield      #723                // Field mindustry/entities/units/StatusEntry.buildSpeedMultiplier:F
     213: fconst_1
     214: fcmpl
     215: ifeq          226
     218: aload_0
     219: aload_1
     220: getfield      #723                // Field mindustry/entities/units/StatusEntry.buildSpeedMultiplier:F
     223: invokevirtual #38                 // Method arc/util/io/Writes.f:(F)V
     226: aload_1
     227: getfield      #726                // Field mindustry/entities/units/StatusEntry.dragMultiplier:F
     230: fconst_1
     231: fcmpl
     232: ifeq          243
     235: aload_0
     236: aload_1
     237: getfield      #726                // Field mindustry/entities/units/StatusEntry.dragMultiplier:F
     240: invokevirtual #38                 // Method arc/util/io/Writes.f:(F)V
     243: aload_1
     244: getfield      #729                // Field mindustry/entities/units/StatusEntry.armorOverride:F
     247: fconst_0
     248: fcmpl
     249: iflt          260
     252: aload_0
     253: aload_1
     254: getfield      #729                // Field mindustry/entities/units/StatusEntry.armorOverride:F
     257: invokevirtual #38                 // Method arc/util/io/Writes.f:(F)V
     260: return

  public static mindustry.entities.units.StatusEntry readStatus(arc.util.io.Reads);
    Code:
       0: aload_0
       1: invokevirtual #240                // Method arc/util/io/Reads.s:()S
       4: istore_1
       5: aload_0
       6: invokevirtual #222                // Method arc/util/io/Reads.f:()F
       9: fstore_2
      10: new           #697                // class mindustry/entities/units/StatusEntry
      13: dup
      14: invokespecial #732                // Method mindustry/entities/units/StatusEntry."<init>":()V
      17: getstatic     #231                // Field mindustry/Vars.content:Lmindustry/core/ContentLoader;
      20: getstatic     #733                // Field mindustry/ctype/ContentType.status:Lmindustry/ctype/ContentType;
      23: iload_1
      24: invokevirtual #243                // Method mindustry/core/ContentLoader.getByID:(Lmindustry/ctype/ContentType;I)Lmindustry/ctype/Content;
      27: checkcast     #703                // class mindustry/type/StatusEffect
      30: fload_2
      31: invokevirtual #737                // Method mindustry/entities/units/StatusEntry.set:(Lmindustry/type/StatusEffect;F)Lmindustry/entities/units/StatusEntry;
      34: astore_3
      35: aload_3
      36: getfield      #696                // Field mindustry/entities/units/StatusEntry.effect:Lmindustry/type/StatusEffect;
      39: getfield      #708                // Field mindustry/type/StatusEffect.dynamic:Z
      42: ifeq          160
      45: aload_0
      46: invokevirtual #315                // Method arc/util/io/Reads.ub:()I
      49: istore        4
      51: iload         4
      53: iconst_1
      54: iand
      55: ifeq          66
      58: aload_3
      59: aload_0
      60: invokevirtual #222                // Method arc/util/io/Reads.f:()F
      63: putfield      #711                // Field mindustry/entities/units/StatusEntry.damageMultiplier:F
      66: iload         4
      68: iconst_2
      69: iand
      70: ifeq          81
      73: aload_3
      74: aload_0
      75: invokevirtual #222                // Method arc/util/io/Reads.f:()F
      78: putfield      #714                // Field mindustry/entities/units/StatusEntry.healthMultiplier:F
      81: iload         4
      83: iconst_4
      84: iand
      85: ifeq          96
      88: aload_3
      89: aload_0
      90: invokevirtual #222                // Method arc/util/io/Reads.f:()F
      93: putfield      #717                // Field mindustry/entities/units/StatusEntry.speedMultiplier:F
      96: iload         4
      98: bipush        8
     100: iand
     101: ifeq          112
     104: aload_3
     105: aload_0
     106: invokevirtual #222                // Method arc/util/io/Reads.f:()F
     109: putfield      #720                // Field mindustry/entities/units/StatusEntry.reloadMultiplier:F
     112: iload         4
     114: bipush        16
     116: iand
     117: ifeq          128
     120: aload_3
     121: aload_0
     122: invokevirtual #222                // Method arc/util/io/Reads.f:()F
     125: putfield      #723                // Field mindustry/entities/units/StatusEntry.buildSpeedMultiplier:F
     128: iload         4
     130: bipush        32
     132: iand
     133: ifeq          144
     136: aload_3
     137: aload_0
     138: invokevirtual #222                // Method arc/util/io/Reads.f:()F
     141: putfield      #726                // Field mindustry/entities/units/StatusEntry.dragMultiplier:F
     144: iload         4
     146: bipush        64
     148: iand
     149: ifeq          160
     152: aload_3
     153: aload_0
     154: invokevirtual #222                // Method arc/util/io/Reads.f:()F
     157: putfield      #729                // Field mindustry/entities/units/StatusEntry.armorOverride:F
     160: aload_3
     161: areturn

  public static void writeItems(arc.util.io.Writes, mindustry.type.ItemStack);
    Code:
       0: aload_0
       1: aload_1
       2: getfield      #740                // Field mindustry/type/ItemStack.item:Lmindustry/type/Item;
       5: invokestatic  #746                // Method writeItem:(Larc/util/io/Writes;Lmindustry/type/Item;)V
       8: aload_0
       9: aload_1
      10: getfield      #750                // Field mindustry/type/ItemStack.amount:I
      13: invokevirtual #19                 // Method arc/util/io/Writes.i:(I)V
      16: return

  public static mindustry.type.ItemStack readItems(arc.util.io.Reads, mindustry.type.ItemStack);
    Code:
       0: aload_1
       1: aload_0
       2: invokestatic  #753                // Method readItem:(Larc/util/io/Reads;)Lmindustry/type/Item;
       5: aload_0
       6: invokevirtual #211                // Method arc/util/io/Reads.i:()I
       9: invokevirtual #757                // Method mindustry/type/ItemStack.set:(Lmindustry/type/Item;I)Lmindustry/type/ItemStack;
      12: areturn

  public static mindustry.type.ItemStack readItems(arc.util.io.Reads);
    Code:
       0: new           #741                // class mindustry/type/ItemStack
       3: dup
       4: aload_0
       5: invokestatic  #753                // Method readItem:(Larc/util/io/Reads;)Lmindustry/type/Item;
       8: aload_0
       9: invokevirtual #211                // Method arc/util/io/Reads.i:()I
      12: invokespecial #760                // Method mindustry/type/ItemStack."<init>":(Lmindustry/type/Item;I)V
      15: areturn

  public static void writeItemStacks(arc.util.io.Writes, mindustry.type.ItemStack[]);
    Code:
       0: aload_0
       1: aload_1
       2: arraylength
       3: invokevirtual #65                 // Method arc/util/io/Writes.s:(I)V
       6: aload_1
       7: astore_2
       8: aload_2
       9: arraylength
      10: istore_3
      11: iconst_0
      12: istore        4
      14: iload         4
      16: iload_3
      17: if_icmpge     38
      20: aload_2
      21: iload         4
      23: aaload
      24: astore        5
      26: aload_0
      27: aload         5
      29: invokestatic  #763                // Method writeItems:(Larc/util/io/Writes;Lmindustry/type/ItemStack;)V
      32: iinc          4, 1
      35: goto          14
      38: return

  public static mindustry.type.ItemStack[] readItemStacks(arc.util.io.Reads);
    Code:
       0: aload_0
       1: invokevirtual #240                // Method arc/util/io/Reads.s:()S
       4: istore_1
       5: iload_1
       6: anewarray     #741                // class mindustry/type/ItemStack
       9: astore_2
      10: iconst_0
      11: istore_3
      12: iload_3
      13: iload_1
      14: if_icmpge     30
      17: aload_2
      18: iload_3
      19: aload_0
      20: invokestatic  #767                // Method readItems:(Larc/util/io/Reads;)Lmindustry/type/ItemStack;
      23: aastore
      24: iinc          3, 1
      27: goto          12
      30: aload_2
      31: areturn

  public static void writeLiquidStacks(arc.util.io.Writes, mindustry.type.LiquidStack[]);
    Code:
       0: aload_0
       1: aload_1
       2: arraylength
       3: invokevirtual #65                 // Method arc/util/io/Writes.s:(I)V
       6: aload_1
       7: astore_2
       8: aload_2
       9: arraylength
      10: istore_3
      11: iconst_0
      12: istore        4
      14: iload         4
      16: iload_3
      17: if_icmpge     50
      20: aload_2
      21: iload         4
      23: aaload
      24: astore        5
      26: aload_0
      27: aload         5
      29: getfield      #771                // Field mindustry/type/LiquidStack.liquid:Lmindustry/type/Liquid;
      32: invokestatic  #777                // Method writeLiquid:(Larc/util/io/Writes;Lmindustry/type/Liquid;)V
      35: aload_0
      36: aload         5
      38: getfield      #781                // Field mindustry/type/LiquidStack.amount:F
      41: invokevirtual #38                 // Method arc/util/io/Writes.f:(F)V
      44: iinc          4, 1
      47: goto          14
      50: return

  public static mindustry.type.LiquidStack[] readLiquidStacks(arc.util.io.Reads);
    Code:
       0: aload_0
       1: invokevirtual #240                // Method arc/util/io/Reads.s:()S
       4: istore_1
       5: iload_1
       6: anewarray     #772                // class mindustry/type/LiquidStack
       9: astore_2
      10: iconst_0
      11: istore_3
      12: iload_3
      13: iload_1
      14: if_icmpge     45
      17: aload_0
      18: invokestatic  #783                // Method readLiquid:(Larc/util/io/Reads;)Lmindustry/type/Liquid;
      21: astore        4
      23: aload_2
      24: iload_3
      25: new           #772                // class mindustry/type/LiquidStack
      28: dup
      29: aload         4
      31: aload_0
      32: invokevirtual #222                // Method arc/util/io/Reads.f:()F
      35: invokespecial #787                // Method mindustry/type/LiquidStack."<init>":(Lmindustry/type/Liquid;F)V
      38: aastore
      39: iinc          3, 1
      42: goto          12
      45: aload_2
      46: areturn

  public static void writeTeam(arc.util.io.Writes, mindustry.game.Team);
    Code:
       0: aload_0
       1: aload_1
       2: ifnonnull     9
       5: iconst_0
       6: goto          13
       9: aload_1
      10: getfield      #158                // Field mindustry/game/Team.id:I
      13: invokevirtual #7                  // Method arc/util/io/Writes.b:(I)V
      16: return

  public static mindustry.game.Team readTeam(arc.util.io.Reads);
    Code:
       0: aload_0
       1: invokevirtual #206                // Method arc/util/io/Reads.b:()B
       4: invokestatic  #790                // Method mindustry/game/Team.get:(I)Lmindustry/game/Team;
       7: areturn

  public static void writeAction(arc.util.io.Writes, mindustry.net.Packets$AdminAction);
    Code:
       0: aload_0
       1: aload_1
       2: invokevirtual #793                // Method mindustry/net/Packets$AdminAction.ordinal:()I
       5: i2b
       6: invokevirtual #7                  // Method arc/util/io/Writes.b:(I)V
       9: return

  public static mindustry.net.Packets$AdminAction readAction(arc.util.io.Reads);
    Code:
       0: getstatic     #796                // Field mindustry/net/Packets$AdminAction.all:[Lmindustry/net/Packets$AdminAction;
       3: aload_0
       4: invokevirtual #206                // Method arc/util/io/Reads.b:()B
       7: aaload
       8: areturn

  public static void writeUnitType(arc.util.io.Writes, mindustry.type.UnitType);
    Code:
       0: aload_0
       1: aload_1
       2: getfield      #799                // Field mindustry/type/UnitType.id:S
       5: invokevirtual #65                 // Method arc/util/io/Writes.s:(I)V
       8: return

  public static mindustry.type.UnitType readUnitType(arc.util.io.Reads);
    Code:
       0: getstatic     #231                // Field mindustry/Vars.content:Lmindustry/core/ContentLoader;
       3: getstatic     #802                // Field mindustry/ctype/ContentType.unit:Lmindustry/ctype/ContentType;
       6: aload_0
       7: invokevirtual #240                // Method arc/util/io/Reads.s:()S
      10: invokevirtual #243                // Method mindustry/core/ContentLoader.getByID:(Lmindustry/ctype/ContentType;I)Lmindustry/ctype/Content;
      13: checkcast     #800                // class mindustry/type/UnitType
      16: areturn

  public static void writeEffect(arc.util.io.Writes, mindustry.entities.Effect);
    Code:
       0: aload_0
       1: aload_1
       2: getfield      #804                // Field mindustry/entities/Effect.id:I
       5: invokevirtual #65                 // Method arc/util/io/Writes.s:(I)V
       8: return

  public static mindustry.entities.Effect readEffect(arc.util.io.Reads);
    Code:
       0: aload_0
       1: invokevirtual #322                // Method arc/util/io/Reads.us:()I
       4: invokestatic  #807                // Method mindustry/entities/Effect.get:(I)Lmindustry/entities/Effect;
       7: areturn

  public static void writeColor(arc.util.io.Writes, arc.graphics.Color);
    Code:
       0: aload_0
       1: aload_1
       2: invokevirtual #810                // Method arc/graphics/Color.rgba:()I
       5: invokevirtual #19                 // Method arc/util/io/Writes.i:(I)V
       8: return

  public static arc.graphics.Color readColor(arc.util.io.Reads);
    Code:
       0: new           #811                // class arc/graphics/Color
       3: dup
       4: aload_0
       5: invokevirtual #211                // Method arc/util/io/Reads.i:()I
       8: invokespecial #815                // Method arc/graphics/Color."<init>":(I)V
      11: areturn

  public static arc.graphics.Color readColor(arc.util.io.Reads, arc.graphics.Color);
    Code:
       0: aload_1
       1: aload_0
       2: invokevirtual #211                // Method arc/util/io/Reads.i:()I
       5: invokevirtual #816                // Method arc/graphics/Color.set:(I)Larc/graphics/Color;
       8: areturn

  public static void writeIntSeq(arc.util.io.Writes, arc.struct.IntSeq);
    Code:
       0: aload_0
       1: aload_1
       2: getfield      #70                 // Field arc/struct/IntSeq.size:I
       5: invokevirtual #19                 // Method arc/util/io/Writes.i:(I)V
       8: iconst_0
       9: istore_2
      10: iload_2
      11: aload_1
      12: getfield      #70                 // Field arc/struct/IntSeq.size:I
      15: if_icmpge     34
      18: aload_0
      19: aload_1
      20: getfield      #74                 // Field arc/struct/IntSeq.items:[I
      23: iload_2
      24: iaload
      25: invokevirtual #19                 // Method arc/util/io/Writes.i:(I)V
      28: iinc          2, 1
      31: goto          10
      34: return

  public static arc.struct.IntSeq readIntSeq(arc.util.io.Reads);
    Code:
       0: aload_0
       1: invokevirtual #211                // Method arc/util/io/Reads.i:()I
       4: istore_1
       5: new           #68                 // class arc/struct/IntSeq
       8: dup
       9: iload_1
      10: invokespecial #254                // Method arc/struct/IntSeq."<init>":(I)V
      13: astore_2
      14: iconst_0
      15: istore_3
      16: iload_3
      17: iload_1
      18: if_icmpge     37
      21: aload_2
      22: getfield      #74                 // Field arc/struct/IntSeq.items:[I
      25: iload_3
      26: aload_0
      27: invokevirtual #211                // Method arc/util/io/Reads.i:()I
      30: iastore
      31: iinc          3, 1
      34: goto          16
      37: aload_2
      38: iload_1
      39: putfield      #70                 // Field arc/struct/IntSeq.size:I
      42: aload_2
      43: areturn

  public static void writeContent(arc.util.io.Writes, mindustry.ctype.Content);
    Code:
       0: aload_0
       1: aload_1
       2: invokevirtual #52                 // Method mindustry/ctype/Content.getContentType:()Lmindustry/ctype/ContentType;
       5: invokevirtual #56                 // Method mindustry/ctype/ContentType.ordinal:()I
       8: invokevirtual #7                  // Method arc/util/io/Writes.b:(I)V
      11: aload_0
      12: aload_1
      13: getfield      #61                 // Field mindustry/ctype/Content.id:S
      16: invokevirtual #65                 // Method arc/util/io/Writes.s:(I)V
      19: return

  public static mindustry.ctype.Content readContent(arc.util.io.Reads);
    Code:
       0: aload_0
       1: invokevirtual #206                // Method arc/util/io/Reads.b:()B
       4: istore_1
       5: getstatic     #231                // Field mindustry/Vars.content:Lmindustry/core/ContentLoader;
       8: getstatic     #236                // Field mindustry/ctype/ContentType.all:[Lmindustry/ctype/ContentType;
      11: iload_1
      12: aaload
      13: aload_0
      14: invokevirtual #240                // Method arc/util/io/Reads.s:()S
      17: invokevirtual #243                // Method mindustry/core/ContentLoader.getByID:(Lmindustry/ctype/ContentType;I)Lmindustry/ctype/Content;
      20: areturn

  public static void writeLiquid(arc.util.io.Writes, mindustry.type.Liquid);
    Code:
       0: aload_0
       1: aload_1
       2: ifnonnull     9
       5: iconst_m1
       6: goto          13
       9: aload_1
      10: getfield      #819                // Field mindustry/type/Liquid.id:S
      13: invokevirtual #65                 // Method arc/util/io/Writes.s:(I)V
      16: return

  public static mindustry.type.Liquid readLiquid(arc.util.io.Reads);
    Code:
       0: aload_0
       1: invokevirtual #240                // Method arc/util/io/Reads.s:()S
       4: istore_1
       5: iload_1
       6: iconst_m1
       7: if_icmpne     14
      10: aconst_null
      11: goto          21
      14: getstatic     #231                // Field mindustry/Vars.content:Lmindustry/core/ContentLoader;
      17: iload_1
      18: invokevirtual #822                // Method mindustry/core/ContentLoader.liquid:(I)Lmindustry/type/Liquid;
      21: areturn

  public static void writeBulletType(arc.util.io.Writes, mindustry.entities.bullet.BulletType);
    Code:
       0: aload_0
       1: aload_1
       2: getfield      #825                // Field mindustry/entities/bullet/BulletType.id:S
       5: invokevirtual #65                 // Method arc/util/io/Writes.s:(I)V
       8: return

  public static mindustry.entities.bullet.BulletType readBulletType(arc.util.io.Reads);
    Code:
       0: getstatic     #231                // Field mindustry/Vars.content:Lmindustry/core/ContentLoader;
       3: getstatic     #828                // Field mindustry/ctype/ContentType.bullet:Lmindustry/ctype/ContentType;
       6: aload_0
       7: invokevirtual #240                // Method arc/util/io/Reads.s:()S
      10: invokevirtual #243                // Method mindustry/core/ContentLoader.getByID:(Lmindustry/ctype/ContentType;I)Lmindustry/ctype/Content;
      13: checkcast     #826                // class mindustry/entities/bullet/BulletType
      16: areturn

  public static void writeItem(arc.util.io.Writes, mindustry.type.Item);
    Code:
       0: aload_0
       1: aload_1
       2: ifnonnull     9
       5: iconst_m1
       6: goto          13
       9: aload_1
      10: getfield      #831                // Field mindustry/type/Item.id:S
      13: invokevirtual #65                 // Method arc/util/io/Writes.s:(I)V
      16: return

  public static mindustry.type.Item readItem(arc.util.io.Reads);
    Code:
       0: aload_0
       1: invokevirtual #240                // Method arc/util/io/Reads.s:()S
       4: istore_1
       5: iload_1
       6: iconst_m1
       7: if_icmpne     14
      10: aconst_null
      11: goto          21
      14: getstatic     #231                // Field mindustry/Vars.content:Lmindustry/core/ContentLoader;
      17: iload_1
      18: invokevirtual #834                // Method mindustry/core/ContentLoader.item:(I)Lmindustry/type/Item;
      21: areturn

  public static void writeSound(arc.util.io.Writes, arc.audio.Sound);
    Code:
       0: aload_0
       1: aload_1
       2: invokestatic  #837                // Method mindustry/gen/Sounds.getSoundId:(Larc/audio/Sound;)I
       5: invokevirtual #65                 // Method arc/util/io/Writes.s:(I)V
       8: return

  public static arc.audio.Sound readSound(arc.util.io.Reads);
    Code:
       0: aload_0
       1: invokevirtual #240                // Method arc/util/io/Reads.s:()S
       4: invokestatic  #843                // Method mindustry/gen/Sounds.getSound:(I)Larc/audio/Sound;
       7: areturn

  public static void writeWeather(arc.util.io.Writes, mindustry.type.Weather);
    Code:
       0: aload_0
       1: aload_1
       2: ifnonnull     9
       5: iconst_m1
       6: goto          13
       9: aload_1
      10: getfield      #847                // Field mindustry/type/Weather.id:S
      13: invokevirtual #65                 // Method arc/util/io/Writes.s:(I)V
      16: return

  public static mindustry.type.Weather readWeather(arc.util.io.Reads);
    Code:
       0: aload_0
       1: invokevirtual #240                // Method arc/util/io/Reads.s:()S
       4: istore_1
       5: iload_1
       6: iconst_m1
       7: if_icmpne     14
      10: aconst_null
      11: goto          27
      14: getstatic     #231                // Field mindustry/Vars.content:Lmindustry/core/ContentLoader;
      17: getstatic     #850                // Field mindustry/ctype/ContentType.weather:Lmindustry/ctype/ContentType;
      20: iload_1
      21: invokevirtual #243                // Method mindustry/core/ContentLoader.getByID:(Lmindustry/ctype/ContentType;I)Lmindustry/ctype/Content;
      24: checkcast     #848                // class mindustry/type/Weather
      27: areturn

  public static void writeString(arc.util.io.Writes, java.lang.String);
    Code:
       0: aload_1
       1: ifnull        17
       4: aload_0
       5: iconst_1
       6: invokevirtual #7                  // Method arc/util/io/Writes.b:(I)V
       9: aload_0
      10: aload_1
      11: invokevirtual #853                // Method arc/util/io/Writes.str:(Ljava/lang/String;)V
      14: goto          22
      17: aload_0
      18: iconst_0
      19: invokevirtual #7                  // Method arc/util/io/Writes.b:(I)V
      22: return

  public static java.lang.String readString(arc.util.io.Reads);
    Code:
       0: aload_0
       1: invokevirtual #206                // Method arc/util/io/Reads.b:()B
       4: istore_1
       5: iload_1
       6: ifeq          14
       9: aload_0
      10: invokevirtual #856                // Method arc/util/io/Reads.str:()Ljava/lang/String;
      13: areturn
      14: aconst_null
      15: areturn

  public static void writeString(java.nio.ByteBuffer, java.lang.String);
    Code:
       0: aload_1
       1: ifnull        29
       4: aload_1
       5: getstatic     #661                // Field mindustry/Vars.charset:Ljava/nio/charset/Charset;
       8: invokevirtual #665                // Method java/lang/String.getBytes:(Ljava/nio/charset/Charset;)[B
      11: astore_2
      12: aload_0
      13: aload_2
      14: arraylength
      15: i2s
      16: invokevirtual #858                // Method java/nio/ByteBuffer.putShort:(S)Ljava/nio/ByteBuffer;
      19: pop
      20: aload_0
      21: aload_2
      22: invokevirtual #864                // Method java/nio/ByteBuffer.put:([B)Ljava/nio/ByteBuffer;
      25: pop
      26: goto          35
      29: aload_0
      30: iconst_m1
      31: invokevirtual #858                // Method java/nio/ByteBuffer.putShort:(S)Ljava/nio/ByteBuffer;
      34: pop
      35: return

  public static java.lang.String readString(java.nio.ByteBuffer);
    Code:
       0: aload_0
       1: invokevirtual #868                // Method java/nio/ByteBuffer.getShort:()S
       4: istore_1
       5: iload_1
       6: iconst_m1
       7: if_icmpeq     32
      10: iload_1
      11: newarray       byte
      13: astore_2
      14: aload_0
      15: aload_2
      16: invokevirtual #871                // Method java/nio/ByteBuffer.get:([B)Ljava/nio/ByteBuffer;
      19: pop
      20: new           #42                 // class java/lang/String
      23: dup
      24: aload_2
      25: getstatic     #661                // Field mindustry/Vars.charset:Ljava/nio/charset/Charset;
      28: invokespecial #669                // Method java/lang/String."<init>":([BLjava/nio/charset/Charset;)V
      31: areturn
      32: aconst_null
      33: areturn

  public static void writeBytes(arc.util.io.Writes, byte[]);
    Code:
       0: aload_0
       1: aload_1
       2: arraylength
       3: i2s
       4: invokevirtual #65                 // Method arc/util/io/Writes.s:(I)V
       7: aload_0
       8: aload_1
       9: invokevirtual #135                // Method arc/util/io/Writes.b:([B)V
      12: return

  public static byte[] readBytes(arc.util.io.Reads);
    Code:
       0: aload_0
       1: invokevirtual #240                // Method arc/util/io/Reads.s:()S
       4: istore_1
       5: aload_0
       6: iload_1
       7: newarray       byte
       9: invokevirtual #294                // Method arc/util/io/Reads.b:([B)[B
      12: areturn

  public static void writeInts(arc.util.io.Writes, int[]);
    Code:
       0: aload_0
       1: aload_1
       2: arraylength
       3: i2s
       4: invokevirtual #65                 // Method arc/util/io/Writes.s:(I)V
       7: aload_1
       8: astore_2
       9: aload_2
      10: arraylength
      11: istore_3
      12: iconst_0
      13: istore        4
      15: iload         4
      17: iload_3
      18: if_icmpge     39
      21: aload_2
      22: iload         4
      24: iaload
      25: istore        5
      27: aload_0
      28: iload         5
      30: invokevirtual #19                 // Method arc/util/io/Writes.i:(I)V
      33: iinc          4, 1
      36: goto          15
      39: return

  public static int[] readInts(arc.util.io.Reads);
    Code:
       0: aload_0
       1: invokevirtual #240                // Method arc/util/io/Reads.s:()S
       4: istore_1
       5: iload_1
       6: newarray       int
       8: astore_2
       9: iconst_0
      10: istore_3
      11: iload_3
      12: iload_1
      13: if_icmpge     29
      16: aload_2
      17: iload_3
      18: aload_0
      19: invokevirtual #211                // Method arc/util/io/Reads.i:()I
      22: iastore
      23: iinc          3, 1
      26: goto          11
      29: aload_2
      30: areturn

  public static void writeTraceInfo(arc.util.io.Writes, mindustry.net.Administration$TraceInfo);
    Code:
       0: aload_0
       1: aload_1
       2: getfield      #873                // Field mindustry/net/Administration$TraceInfo.ip:Ljava/lang/String;
       5: invokestatic  #44                 // Method writeString:(Larc/util/io/Writes;Ljava/lang/String;)V
       8: aload_0
       9: aload_1
      10: getfield      #879                // Field mindustry/net/Administration$TraceInfo.uuid:Ljava/lang/String;
      13: invokestatic  #44                 // Method writeString:(Larc/util/io/Writes;Ljava/lang/String;)V
      16: aload_0
      17: aload_1
      18: getfield      #882                // Field mindustry/net/Administration$TraceInfo.locale:Ljava/lang/String;
      21: invokestatic  #44                 // Method writeString:(Larc/util/io/Writes;Ljava/lang/String;)V
      24: aload_0
      25: aload_1
      26: getfield      #885                // Field mindustry/net/Administration$TraceInfo.modded:Z
      29: ifeq          36
      32: iconst_1
      33: goto          37
      36: iconst_0
      37: invokevirtual #7                  // Method arc/util/io/Writes.b:(I)V
      40: aload_0
      41: aload_1
      42: getfield      #888                // Field mindustry/net/Administration$TraceInfo.mobile:Z
      45: ifeq          52
      48: iconst_1
      49: goto          53
      52: iconst_0
      53: invokevirtual #7                  // Method arc/util/io/Writes.b:(I)V
      56: aload_0
      57: aload_1
      58: getfield      #891                // Field mindustry/net/Administration$TraceInfo.timesJoined:I
      61: invokevirtual #19                 // Method arc/util/io/Writes.i:(I)V
      64: aload_0
      65: aload_1
      66: getfield      #894                // Field mindustry/net/Administration$TraceInfo.timesKicked:I
      69: invokevirtual #19                 // Method arc/util/io/Writes.i:(I)V
      72: aload_0
      73: aload_1
      74: getfield      #897                // Field mindustry/net/Administration$TraceInfo.ips:[Ljava/lang/String;
      77: bipush        12
      79: invokestatic  #901                // Method writeStrings:(Larc/util/io/Writes;[Ljava/lang/String;I)V
      82: aload_0
      83: aload_1
      84: getfield      #905                // Field mindustry/net/Administration$TraceInfo.names:[Ljava/lang/String;
      87: bipush        12
      89: invokestatic  #901                // Method writeStrings:(Larc/util/io/Writes;[Ljava/lang/String;I)V
      92: return

  public static mindustry.net.Administration$TraceInfo readTraceInfo(arc.util.io.Reads);
    Code:
       0: new           #874                // class mindustry/net/Administration$TraceInfo
       3: dup
       4: aload_0
       5: invokestatic  #227                // Method readString:(Larc/util/io/Reads;)Ljava/lang/String;
       8: aload_0
       9: invokestatic  #227                // Method readString:(Larc/util/io/Reads;)Ljava/lang/String;
      12: aload_0
      13: invokestatic  #227                // Method readString:(Larc/util/io/Reads;)Ljava/lang/String;
      16: aload_0
      17: invokevirtual #206                // Method arc/util/io/Reads.b:()B
      20: iconst_1
      21: if_icmpne     28
      24: iconst_1
      25: goto          29
      28: iconst_0
      29: aload_0
      30: invokevirtual #206                // Method arc/util/io/Reads.b:()B
      33: iconst_1
      34: if_icmpne     41
      37: iconst_1
      38: goto          42
      41: iconst_0
      42: aload_0
      43: invokevirtual #211                // Method arc/util/io/Reads.i:()I
      46: aload_0
      47: invokevirtual #211                // Method arc/util/io/Reads.i:()I
      50: aload_0
      51: invokestatic  #908                // Method readStrings:(Larc/util/io/Reads;)[Ljava/lang/String;
      54: aload_0
      55: invokestatic  #908                // Method readStrings:(Larc/util/io/Reads;)[Ljava/lang/String;
      58: invokespecial #912                // Method mindustry/net/Administration$TraceInfo."<init>":(Ljava/lang/String;Ljava/lang/String;Ljava/lang/String;ZZII[Ljava/lang/String;[Ljava/lang/String;)V
      61: areturn

  public static void writeStrings(arc.util.io.Writes, java.lang.String[], int);
    Code:
       0: aload_0
       1: aload_1
       2: arraylength
       3: iload_2
       4: invokestatic  #479                // Method java/lang/Math.min:(II)I
       7: invokevirtual #7                  // Method arc/util/io/Writes.b:(I)V
      10: iconst_0
      11: istore_3
      12: iload_3
      13: aload_1
      14: arraylength
      15: iload_2
      16: invokestatic  #479                // Method java/lang/Math.min:(II)I
      19: if_icmpge     35
      22: aload_0
      23: aload_1
      24: iload_3
      25: aaload
      26: invokestatic  #44                 // Method writeString:(Larc/util/io/Writes;Ljava/lang/String;)V
      29: iinc          3, 1
      32: goto          12
      35: return

  public static void writeStrings(arc.util.io.Writes, java.lang.String[]);
    Code:
       0: aload_0
       1: aload_1
       2: arraylength
       3: invokevirtual #7                  // Method arc/util/io/Writes.b:(I)V
       6: aload_1
       7: astore_2
       8: aload_2
       9: arraylength
      10: istore_3
      11: iconst_0
      12: istore        4
      14: iload         4
      16: iload_3
      17: if_icmpge     38
      20: aload_2
      21: iload         4
      23: aaload
      24: astore        5
      26: aload_0
      27: aload         5
      29: invokestatic  #44                 // Method writeString:(Larc/util/io/Writes;Ljava/lang/String;)V
      32: iinc          4, 1
      35: goto          14
      38: return

  public static java.lang.String[] readStrings(arc.util.io.Reads);
    Code:
       0: aload_0
       1: invokevirtual #315                // Method arc/util/io/Reads.ub:()I
       4: istore_1
       5: iload_1
       6: anewarray     #42                 // class java/lang/String
       9: astore_2
      10: iconst_0
      11: istore_3
      12: iload_3
      13: iload_1
      14: if_icmpge     30
      17: aload_2
      18: iload_3
      19: aload_0
      20: invokestatic  #227                // Method readString:(Larc/util/io/Reads;)Ljava/lang/String;
      23: aastore
      24: iinc          3, 1
      27: goto          12
      30: aload_2
      31: areturn

  public static void writeStringArray(arc.util.io.Writes, java.lang.String[][]);
    Code:
       0: aload_0
       1: aload_1
       2: arraylength
       3: invokevirtual #7                  // Method arc/util/io/Writes.b:(I)V
       6: aload_1
       7: astore_2
       8: aload_2
       9: arraylength
      10: istore_3
      11: iconst_0
      12: istore        4
      14: iload         4
      16: iload_3
      17: if_icmpge     77
      20: aload_2
      21: iload         4
      23: aaload
      24: astore        5
      26: aload_0
      27: aload         5
      29: arraylength
      30: invokevirtual #7                  // Method arc/util/io/Writes.b:(I)V
      33: aload         5
      35: astore        6
      37: aload         6
      39: arraylength
      40: istore        7
      42: iconst_0
      43: istore        8
      45: iload         8
      47: iload         7
      49: if_icmpge     71
      52: aload         6
      54: iload         8
      56: aaload
      57: astore        9
      59: aload_0
      60: aload         9
      62: invokestatic  #44                 // Method writeString:(Larc/util/io/Writes;Ljava/lang/String;)V
      65: iinc          8, 1
      68: goto          45
      71: iinc          4, 1
      74: goto          14
      77: return

  public static java.lang.String[][] readStringArray(arc.util.io.Reads);
    Code:
       0: aload_0
       1: invokevirtual #315                // Method arc/util/io/Reads.ub:()I
       4: istore_1
       5: iload_1
       6: anewarray     #915                // class "[Ljava/lang/String;"
       9: astore_2
      10: iconst_0
      11: istore_3
      12: iload_3
      13: iload_1
      14: if_icmpge     63
      17: aload_0
      18: invokevirtual #315                // Method arc/util/io/Reads.ub:()I
      21: istore        4
      23: aload_2
      24: iload_3
      25: iload         4
      27: anewarray     #42                 // class java/lang/String
      30: aastore
      31: iconst_0
      32: istore        5
      34: iload         5
      36: iload         4
      38: if_icmpge     57
      41: aload_2
      42: iload_3
      43: aaload
      44: iload         5
      46: aload_0
      47: invokestatic  #227                // Method readString:(Larc/util/io/Reads;)Ljava/lang/String;
      50: aastore
      51: iinc          5, 1
      54: goto          34
      57: iinc          3, 1
      60: goto          12
      63: aload_2
      64: areturn

  public static void writeStringData(java.io.DataOutput, java.lang.String) throws java.io.IOException;
    Code:
       0: aload_1
       1: ifnull        31
       4: aload_1
       5: getstatic     #661                // Field mindustry/Vars.charset:Ljava/nio/charset/Charset;
       8: invokevirtual #665                // Method java/lang/String.getBytes:(Ljava/nio/charset/Charset;)[B
      11: astore_2
      12: aload_0
      13: aload_2
      14: arraylength
      15: i2s
      16: invokeinterface #916,  2          // InterfaceMethod java/io/DataOutput.writeShort:(I)V
      21: aload_0
      22: aload_2
      23: invokeinterface #921,  2          // InterfaceMethod java/io/DataOutput.write:([B)V
      28: goto          38
      31: aload_0
      32: iconst_m1
      33: invokeinterface #916,  2          // InterfaceMethod java/io/DataOutput.writeShort:(I)V
      38: return

  public static java.lang.String readStringData(java.io.DataInput) throws java.io.IOException;
    Code:
       0: aload_0
       1: invokeinterface #923,  1          // InterfaceMethod java/io/DataInput.readShort:()S
       6: istore_1
       7: iload_1
       8: iconst_m1
       9: if_icmpeq     35
      12: iload_1
      13: newarray       byte
      15: astore_2
      16: aload_0
      17: aload_2
      18: invokeinterface #928,  2          // InterfaceMethod java/io/DataInput.readFully:([B)V
      23: new           #42                 // class java/lang/String
      26: dup
      27: aload_2
      28: getstatic     #661                // Field mindustry/Vars.charset:Ljava/nio/charset/Charset;
      31: invokespecial #669                // Method java/lang/String."<init>":([BLjava/nio/charset/Charset;)V
      34: areturn
      35: aconst_null
      36: areturn

  static {};
    Code:
       0: iconst_0
       1: anewarray     #343                // class mindustry/entities/units/WeaponMount
       4: putstatic     #360                // Field noMounts:[Lmindustry/entities/units/WeaponMount;
       7: iconst_0
       8: anewarray     #365                // class mindustry/entities/abilities/Ability
      11: putstatic     #369                // Field noAbilities:[Lmindustry/entities/abilities/Ability;
      14: return
}
